{
"meta":{"test_sets":[],"test_metrics":[],"learn_metrics":[{"best_value":"Min","name":"RMSE"}],"launch_mode":"Train","parameters":"","iteration_count":1000,"learn_sets":["learn"],"name":"experiment"},
"iterations":[
{"learn":[9.203319498],"iteration":0,"passed_time":0.002836981132,"remaining_time":2.834144151},
{"learn":[8.80350822],"iteration":1,"passed_time":0.00534879776,"remaining_time":2.669050082},
{"learn":[8.445799441],"iteration":2,"passed_time":0.007891822514,"remaining_time":2.622715682},
{"learn":[8.091306102],"iteration":3,"passed_time":0.01051372174,"remaining_time":2.617916714},
{"learn":[7.803664422],"iteration":4,"passed_time":0.0131659541,"remaining_time":2.620024867},
{"learn":[7.494534351],"iteration":5,"passed_time":0.01558268803,"remaining_time":2.581531984},
{"learn":[7.206967531],"iteration":6,"passed_time":0.0181380877,"remaining_time":2.573017298},
{"learn":[6.964434712],"iteration":7,"passed_time":0.02080156999,"remaining_time":2.579394679},
{"learn":[6.688767066],"iteration":8,"passed_time":0.02327788685,"remaining_time":2.563153986},
{"learn":[6.454265888],"iteration":9,"passed_time":0.02575687037,"remaining_time":2.549930166},
{"learn":[6.209753553],"iteration":10,"passed_time":0.02814477115,"remaining_time":2.530470788},
{"learn":[5.985207711],"iteration":11,"passed_time":0.03054625518,"remaining_time":2.51497501},
{"learn":[5.781161527],"iteration":12,"passed_time":0.03300036386,"remaining_time":2.505489164},
{"learn":[5.584957626],"iteration":13,"passed_time":0.03554426361,"remaining_time":2.503331708},
{"learn":[5.420050063],"iteration":14,"passed_time":0.03804883028,"remaining_time":2.498539855},
{"learn":[5.241305351],"iteration":15,"passed_time":0.04088164477,"remaining_time":2.514221154},
{"learn":[5.061599394],"iteration":16,"passed_time":0.04338558646,"remaining_time":2.508707734},
{"learn":[4.922877309],"iteration":17,"passed_time":0.04580086206,"remaining_time":2.498691475},
{"learn":[4.777214846],"iteration":18,"passed_time":0.04834913678,"remaining_time":2.496342273},
{"learn":[4.633452687],"iteration":19,"passed_time":0.05075353745,"remaining_time":2.486923335},
{"learn":[4.485405897],"iteration":20,"passed_time":0.05318352129,"remaining_time":2.479365112},
{"learn":[4.36354769],"iteration":21,"passed_time":0.05565762984,"remaining_time":2.474234636},
{"learn":[4.249698326],"iteration":22,"passed_time":0.05828844567,"remaining_time":2.475991801},
{"learn":[4.121291618],"iteration":23,"passed_time":0.06083617873,"remaining_time":2.474004602},
{"learn":[4.022887565],"iteration":24,"passed_time":0.06337287019,"remaining_time":2.471541938},
{"learn":[3.919625085],"iteration":25,"passed_time":0.0657779792,"remaining_time":2.464144298},
{"learn":[3.823682657],"iteration":26,"passed_time":0.06804000582,"remaining_time":2.45196021},
{"learn":[3.735458497],"iteration":27,"passed_time":0.07046657301,"remaining_time":2.446196749},
{"learn":[3.640710057],"iteration":28,"passed_time":0.07298805624,"remaining_time":2.443841469},
{"learn":[3.56171861],"iteration":29,"passed_time":0.07552353938,"remaining_time":2.441927773},
{"learn":[3.496192128],"iteration":30,"passed_time":0.07802335609,"remaining_time":2.438859098},
{"learn":[3.40590216],"iteration":31,"passed_time":0.08041725684,"remaining_time":2.432622019},
{"learn":[3.310175075],"iteration":32,"passed_time":0.08275332463,"remaining_time":2.424923179},
{"learn":[3.249469724],"iteration":33,"passed_time":0.08521276661,"remaining_time":2.421045075},
{"learn":[3.185843253],"iteration":34,"passed_time":0.08769779175,"remaining_time":2.417953401},
{"learn":[3.10499707],"iteration":35,"passed_time":0.0900499011,"remaining_time":2.411336241},
{"learn":[3.039414366],"iteration":36,"passed_time":0.09241951035,"remaining_time":2.405405094},
{"learn":[2.961339558],"iteration":37,"passed_time":0.09488361896,"remaining_time":2.402053722},
{"learn":[2.898442147],"iteration":38,"passed_time":0.09754035129,"remaining_time":2.403494297},
{"learn":[2.83173262],"iteration":39,"passed_time":0.1000129598,"remaining_time":2.400311036},
{"learn":[2.773520951],"iteration":40,"passed_time":0.1024533186,"remaining_time":2.396408111},
{"learn":[2.723947914],"iteration":41,"passed_time":0.1050271765,"remaining_time":2.395619883},
{"learn":[2.661989493],"iteration":42,"passed_time":0.1073842442,"remaining_time":2.389923759},
{"learn":[2.597765597],"iteration":43,"passed_time":0.1100355182,"remaining_time":2.390771713},
{"learn":[2.55004419],"iteration":44,"passed_time":0.1123364196,"remaining_time":2.384028459},
{"learn":[2.507055935],"iteration":45,"passed_time":0.1147625701,"remaining_time":2.38007591},
{"learn":[2.467617103],"iteration":46,"passed_time":0.1171406793,"remaining_time":2.375214199},
{"learn":[2.41884711],"iteration":47,"passed_time":0.1193209981,"remaining_time":2.366533129},
{"learn":[2.364685502],"iteration":48,"passed_time":0.1218578979,"remaining_time":2.365037977},
{"learn":[2.327248546],"iteration":49,"passed_time":0.1241711325,"remaining_time":2.359251518},
{"learn":[2.298029247],"iteration":50,"passed_time":0.1268906978,"remaining_time":2.361162199},
{"learn":[2.252089218],"iteration":51,"passed_time":0.1297825119,"remaining_time":2.366035024},
{"learn":[2.206737393],"iteration":52,"passed_time":0.1321308712,"remaining_time":2.360904435},
{"learn":[2.169611689],"iteration":53,"passed_time":0.1347212707,"remaining_time":2.360117075},
{"learn":[2.128352115],"iteration":54,"passed_time":0.1370655468,"remaining_time":2.355035303},
{"learn":[2.100036081],"iteration":55,"passed_time":0.1394679474,"remaining_time":2.351031114},
{"learn":[2.071277062],"iteration":56,"passed_time":0.14183639,"remaining_time":2.34652133},
{"learn":[2.027735002],"iteration":57,"passed_time":0.144247124,"remaining_time":2.342772255},
{"learn":[1.994337367],"iteration":58,"passed_time":0.1466328998,"remaining_time":2.338670486},
{"learn":[1.961901914],"iteration":59,"passed_time":0.1489404261,"remaining_time":2.333400009},
{"learn":[1.935270256],"iteration":60,"passed_time":0.1513818682,"remaining_time":2.330288102},
{"learn":[1.904835406],"iteration":61,"passed_time":0.1537492691,"remaining_time":2.326077652},
{"learn":[1.879712035],"iteration":62,"passed_time":0.1562360859,"remaining_time":2.323701786},
{"learn":[1.858532082],"iteration":63,"passed_time":0.1587528608,"remaining_time":2.32176059},
{"learn":[1.830450338],"iteration":64,"passed_time":0.1611760947,"remaining_time":2.318456132},
{"learn":[1.803936598],"iteration":65,"passed_time":0.1636132035,"remaining_time":2.315374729},
{"learn":[1.780088195],"iteration":66,"passed_time":0.1664494347,"remaining_time":2.317870486},
{"learn":[1.762520545],"iteration":67,"passed_time":0.1687107113,"remaining_time":2.312329161},
{"learn":[1.742809977],"iteration":68,"passed_time":0.1710896538,"remaining_time":2.308470546},
{"learn":[1.72159103],"iteration":69,"passed_time":0.1737006781,"remaining_time":2.30773758},
{"learn":[1.701005325],"iteration":70,"passed_time":0.1763562021,"remaining_time":2.307533968},
{"learn":[1.680846875],"iteration":71,"passed_time":0.1788198524,"remaining_time":2.304789209},
{"learn":[1.658737391],"iteration":72,"passed_time":0.1816682918,"remaining_time":2.306938445},
{"learn":[1.637050891],"iteration":73,"passed_time":0.1840754841,"remaining_time":2.303431058},
{"learn":[1.618696315],"iteration":74,"passed_time":0.1864834264,"remaining_time":2.299962259},
{"learn":[1.599949077],"iteration":75,"passed_time":0.1888690356,"remaining_time":2.296249853},
{"learn":[1.584867799],"iteration":76,"passed_time":0.1911466454,"remaining_time":2.291277321},
{"learn":[1.570673253],"iteration":77,"passed_time":0.1936051707,"remaining_time":2.288512403},
{"learn":[1.559114776],"iteration":78,"passed_time":0.1960829042,"remaining_time":2.285979175},
{"learn":[1.54661765],"iteration":79,"passed_time":0.1984410552,"remaining_time":2.282072135},
{"learn":[1.535593695],"iteration":80,"passed_time":0.2006567072,"remaining_time":2.276586591},
{"learn":[1.521176721],"iteration":81,"passed_time":0.2030445246,"remaining_time":2.273108215},
{"learn":[1.511184832],"iteration":82,"passed_time":0.2054863,"remaining_time":2.270252255},
{"learn":[1.500002242],"iteration":83,"passed_time":0.207800868,"remaining_time":2.266018989},
{"learn":[1.485875905],"iteration":84,"passed_time":0.2101228942,"remaining_time":2.261911155},
{"learn":[1.478216112],"iteration":85,"passed_time":0.2124071707,"remaining_time":2.257443651},
{"learn":[1.464631185],"iteration":86,"passed_time":0.2146690306,"remaining_time":2.252791092},
{"learn":[1.455288432],"iteration":87,"passed_time":0.2168866826,"remaining_time":2.24773471},
{"learn":[1.444307901],"iteration":88,"passed_time":0.2191909589,"remaining_time":2.243628804},
{"learn":[1.428640508],"iteration":89,"passed_time":0.2216168594,"remaining_time":2.24079269},
{"learn":[1.420668845],"iteration":90,"passed_time":0.2246162145,"remaining_time":2.243693835},
{"learn":[1.416601057],"iteration":91,"passed_time":0.2269364907,"remaining_time":2.239764495},
{"learn":[1.401719918],"iteration":92,"passed_time":0.229248892,"remaining_time":2.235792957},
{"learn":[1.393644327],"iteration":93,"passed_time":0.2313812112,"remaining_time":2.230121035},
{"learn":[1.381510129],"iteration":94,"passed_time":0.2336828625,"remaining_time":2.226136743},
{"learn":[1.373886466],"iteration":95,"passed_time":0.235971889,"remaining_time":2.222068621},
{"learn":[1.360327748],"iteration":96,"passed_time":0.2384193727,"remaining_time":2.219512304},
{"learn":[1.351391947],"iteration":97,"passed_time":0.2408636481,"remaining_time":2.216928679},
{"learn":[1.346422771],"iteration":98,"passed_time":0.243480839,"remaining_time":2.215921575},
{"learn":[1.337119155],"iteration":99,"passed_time":0.2457716988,"remaining_time":2.211945289},
{"learn":[1.327298719],"iteration":100,"passed_time":0.248239349,"remaining_time":2.209575988},
{"learn":[1.321131052],"iteration":101,"passed_time":0.2506789578,"remaining_time":2.206957883},
{"learn":[1.313318264],"iteration":102,"passed_time":0.2532345658,"remaining_time":2.205353452},
{"learn":[1.303564522],"iteration":103,"passed_time":0.2557025077,"remaining_time":2.202975451},
{"learn":[1.296573431],"iteration":104,"passed_time":0.2581396165,"remaining_time":2.200332922},
{"learn":[1.293302975],"iteration":105,"passed_time":0.2605401839,"remaining_time":2.197386079},
{"learn":[1.285352004],"iteration":106,"passed_time":0.2627704607,"remaining_time":2.193028238},
{"learn":[1.277961457],"iteration":107,"passed_time":0.2651383616,"remaining_time":2.189846468},
{"learn":[1.268024202],"iteration":108,"passed_time":0.2675975536,"remaining_time":2.187425874},
{"learn":[1.263648354],"iteration":109,"passed_time":0.2700737455,"remaining_time":2.185142123},
{"learn":[1.252692025],"iteration":110,"passed_time":0.2724354798,"remaining_time":2.181938212},
{"learn":[1.243487546],"iteration":111,"passed_time":0.275054504,"remaining_time":2.180789282},
{"learn":[1.239189511],"iteration":112,"passed_time":0.2774750296,"remaining_time":2.178056206},
{"learn":[1.23327176],"iteration":113,"passed_time":0.2797538894,"remaining_time":2.174227597},
{"learn":[1.227158784],"iteration":114,"passed_time":0.2824104551,"remaining_time":2.173332633},
{"learn":[1.221534628],"iteration":115,"passed_time":0.2850745207,"remaining_time":2.172464451},
{"learn":[1.214749142],"iteration":116,"passed_time":0.287494088,"remaining_time":2.169720339},
{"learn":[1.21049102],"iteration":117,"passed_time":0.2897645729,"remaining_time":2.165867401},
{"learn":[1.204876388],"iteration":118,"passed_time":0.2919744748,"remaining_time":2.161592541},
{"learn":[1.197507594],"iteration":119,"passed_time":0.2946437487,"remaining_time":2.160720824},
{"learn":[1.19206467],"iteration":120,"passed_time":0.2974311469,"remaining_time":2.160677505},
{"learn":[1.185544846],"iteration":121,"passed_time":0.2999480468,"remaining_time":2.158642501},
{"learn":[1.180575715],"iteration":122,"passed_time":0.3022648231,"remaining_time":2.155172763},
{"learn":[1.173719964],"iteration":123,"passed_time":0.3049013889,"remaining_time":2.153980779},
{"learn":[1.168436104],"iteration":124,"passed_time":0.3072890396,"remaining_time":2.151023278},
{"learn":[1.163465921],"iteration":125,"passed_time":0.3097071486,"remaining_time":2.148286094},
{"learn":[1.157315844],"iteration":126,"passed_time":0.3126410457,"remaining_time":2.149099472},
{"learn":[1.150932202],"iteration":127,"passed_time":0.3154694852,"remaining_time":2.149135868},
{"learn":[1.148009589],"iteration":128,"passed_time":0.3178382195,"remaining_time":2.146023947},
{"learn":[1.144160683],"iteration":129,"passed_time":0.3201258293,"remaining_time":2.14238055},
{"learn":[1.139678547],"iteration":130,"passed_time":0.3227017288,"remaining_time":2.140670247},
{"learn":[1.136457236],"iteration":131,"passed_time":0.3250170051,"remaining_time":2.137233033},
{"learn":[1.132914551],"iteration":132,"passed_time":0.3274301974,"remaining_time":2.134450986},
{"learn":[1.129682046],"iteration":133,"passed_time":0.3301314294,"remaining_time":2.133535954},
{"learn":[1.126373011],"iteration":134,"passed_time":0.3324387057,"remaining_time":2.130070226},
{"learn":[1.12369964],"iteration":135,"passed_time":0.3347658152,"remaining_time":2.126747532},
{"learn":[1.120855768],"iteration":136,"passed_time":0.3373966311,"remaining_time":2.125352501},
{"learn":[1.117874267],"iteration":137,"passed_time":0.3396392828,"remaining_time":2.121514941},
{"learn":[1.115517716],"iteration":138,"passed_time":0.3418822262,"remaining_time":2.117702135},
{"learn":[1.112197114],"iteration":139,"passed_time":0.3442173774,"remaining_time":2.114478175},
{"learn":[1.107589194],"iteration":140,"passed_time":0.3465907366,"remaining_time":2.111499594},
{"learn":[1.099401476],"iteration":141,"passed_time":0.3492224274,"remaining_time":2.110090442},
{"learn":[1.096296982],"iteration":142,"passed_time":0.3514927873,"remaining_time":2.106498732},
{"learn":[1.091895432],"iteration":143,"passed_time":0.3539956457,"remaining_time":2.104307449},
{"learn":[1.086882835],"iteration":144,"passed_time":0.3569825425,"remaining_time":2.104966026},
{"learn":[1.083517937],"iteration":145,"passed_time":0.3592951104,"remaining_time":2.101630303},
{"learn":[1.079754897],"iteration":146,"passed_time":0.3616280949,"remaining_time":2.098426973},
{"learn":[1.077445016],"iteration":147,"passed_time":0.3638152054,"remaining_time":2.094395642},
{"learn":[1.073383433],"iteration":148,"passed_time":0.3664366463,"remaining_time":2.092869705},
{"learn":[1.071205163],"iteration":149,"passed_time":0.3688882966,"remaining_time":2.090367014},
{"learn":[1.067844555],"iteration":150,"passed_time":0.3714388213,"remaining_time":2.088420923},
{"learn":[1.065620563],"iteration":151,"passed_time":0.3738163472,"remaining_time":2.085501726},
{"learn":[1.063226417],"iteration":152,"passed_time":0.3763372054,"remaining_time":2.083383091},
{"learn":[1.061624659],"iteration":153,"passed_time":0.3793492687,"remaining_time":2.083957671},
{"learn":[1.059718062],"iteration":154,"passed_time":0.3817087947,"remaining_time":2.08092859},
{"learn":[1.055863334],"iteration":155,"passed_time":0.3843553188,"remaining_time":2.079460827},
{"learn":[1.053450973],"iteration":156,"passed_time":0.3866636367,"remaining_time":2.076162075},
{"learn":[1.051532726],"iteration":157,"passed_time":0.3888722054,"remaining_time":2.072344284},
{"learn":[1.048420755],"iteration":158,"passed_time":0.3914721048,"remaining_time":2.070616604},
{"learn":[1.04555404],"iteration":159,"passed_time":0.3938072976,"remaining_time":2.067488312},
{"learn":[1.043194148],"iteration":160,"passed_time":0.3962276565,"remaining_time":2.064813688},
{"learn":[1.04094317],"iteration":161,"passed_time":0.3988208892,"remaining_time":2.063036452},
{"learn":[1.038270943],"iteration":162,"passed_time":0.4010561244,"remaining_time":2.059410896},
{"learn":[1.036407512],"iteration":163,"passed_time":0.4034866082,"remaining_time":2.056797588},
{"learn":[1.034352929],"iteration":164,"passed_time":0.4058820506,"remaining_time":2.054009165},
{"learn":[1.032542166],"iteration":165,"passed_time":0.4082106184,"remaining_time":2.050889493},
{"learn":[1.029896922],"iteration":166,"passed_time":0.4104486452,"remaining_time":2.047327673},
{"learn":[1.028324501],"iteration":167,"passed_time":0.412840921,"remaining_time":2.044545513},
{"learn":[1.02660741],"iteration":168,"passed_time":0.415148864,"remaining_time":2.04135329},
{"learn":[1.024860978],"iteration":169,"passed_time":0.4176455557,"remaining_time":2.039093007},
{"learn":[1.021737464],"iteration":170,"passed_time":0.4201099143,"remaining_time":2.03667321},
{"learn":[1.019618206],"iteration":171,"passed_time":0.4223797325,"remaining_time":2.033316387},
{"learn":[1.017869195],"iteration":172,"passed_time":0.4248990908,"remaining_time":2.031165018},
{"learn":[1.016056242],"iteration":173,"passed_time":0.4273220747,"remaining_time":2.028551918},
{"learn":[1.01433034],"iteration":174,"passed_time":0.4295673514,"remaining_time":2.025103228},
{"learn":[1.012224463],"iteration":175,"passed_time":0.4321068345,"remaining_time":2.023045634},
{"learn":[1.01028354],"iteration":176,"passed_time":0.434489527,"remaining_time":2.020253563},
{"learn":[1.00922341],"iteration":177,"passed_time":0.4370093436,"remaining_time":2.018099328},
{"learn":[1.007334165],"iteration":178,"passed_time":0.4393782028,"remaining_time":2.015248629},
{"learn":[1.006126697],"iteration":179,"passed_time":0.4416252295,"remaining_time":2.011848268},
{"learn":[1.005046138],"iteration":180,"passed_time":0.4440058804,"remaining_time":2.009065282},
{"learn":[1.003836251],"iteration":181,"passed_time":0.446172241,"remaining_time":2.005323589},
{"learn":[1.002576762],"iteration":182,"passed_time":0.448629933,"remaining_time":2.002899755},
{"learn":[1.001388074],"iteration":183,"passed_time":0.4509836673,"remaining_time":2.000014525},
{"learn":[0.9998981982],"iteration":184,"passed_time":0.4535471919,"remaining_time":1.998059251},
{"learn":[0.9990504254],"iteration":185,"passed_time":0.4560245088,"remaining_time":1.995720162},
{"learn":[0.9977648065],"iteration":186,"passed_time":0.4583434934,"remaining_time":1.99269123},
{"learn":[0.9964660798],"iteration":187,"passed_time":0.4609376428,"remaining_time":1.990858329},
{"learn":[0.9947665243],"iteration":188,"passed_time":0.4634570844,"remaining_time":1.988696801},
{"learn":[0.9937588986],"iteration":189,"passed_time":0.46586911,"remaining_time":1.986073574},
{"learn":[0.9924153183],"iteration":190,"passed_time":0.4683287186,"remaining_time":1.983654101},
{"learn":[0.9913322589],"iteration":191,"passed_time":0.4709144098,"remaining_time":1.981764808},
{"learn":[0.9890018093],"iteration":192,"passed_time":0.4736610582,"remaining_time":1.980541316},
{"learn":[0.9876811482],"iteration":193,"passed_time":0.4760730004,"remaining_time":1.977911538},
{"learn":[0.9862580795],"iteration":194,"passed_time":0.4783608186,"remaining_time":1.974771584},
{"learn":[0.9847842682],"iteration":195,"passed_time":0.480799094,"remaining_time":1.972257508},
{"learn":[0.9838389545],"iteration":196,"passed_time":0.4831434534,"remaining_time":1.969361386},
{"learn":[0.9829832768],"iteration":197,"passed_time":0.4854055634,"remaining_time":1.966137686},
{"learn":[0.9818109221],"iteration":198,"passed_time":0.4876361735,"remaining_time":1.962796859},
{"learn":[0.9808567093],"iteration":199,"passed_time":0.4899876579,"remaining_time":1.959950632},
{"learn":[0.9800248444],"iteration":200,"passed_time":0.4924935996,"remaining_time":1.957723314},
{"learn":[0.9779821632],"iteration":201,"passed_time":0.4947672094,"remaining_time":1.954575412},
{"learn":[0.976899298],"iteration":202,"passed_time":0.497197485,"remaining_time":1.952051209},
{"learn":[0.9759059728],"iteration":203,"passed_time":0.4996148855,"remaining_time":1.949477691},
{"learn":[0.974856035],"iteration":204,"passed_time":0.5018609956,"remaining_time":1.946241422},
{"learn":[0.9710259963],"iteration":205,"passed_time":0.5042462714,"remaining_time":1.943551163},
{"learn":[0.9693858886],"iteration":206,"passed_time":0.5072513764,"remaining_time":1.943238365},
{"learn":[0.9685848772],"iteration":207,"passed_time":0.5096416522,"remaining_time":1.940558599},
{"learn":[0.9671614938],"iteration":208,"passed_time":0.5118890956,"remaining_time":1.937341027},
{"learn":[0.9662655285],"iteration":209,"passed_time":0.5144283287,"remaining_time":1.935230379},
{"learn":[0.9646945624],"iteration":210,"passed_time":0.5169129788,"remaining_time":1.932911565},
{"learn":[0.9633129254],"iteration":211,"passed_time":0.519640919,"remaining_time":1.931495491},
{"learn":[0.9624137601],"iteration":212,"passed_time":0.5219001957,"remaining_time":1.928335465},
{"learn":[0.9612654743],"iteration":213,"passed_time":0.5243054297,"remaining_time":1.925719943},
{"learn":[0.96023604],"iteration":214,"passed_time":0.5268276212,"remaining_time":1.923533408},
{"learn":[0.9592798325],"iteration":215,"passed_time":0.5290270233,"remaining_time":1.920172159},
{"learn":[0.9585094367],"iteration":216,"passed_time":0.5318090048,"remaining_time":1.918923736},
{"learn":[0.9579940573],"iteration":217,"passed_time":0.5341280727,"remaining_time":1.916000701},
{"learn":[0.9567057704],"iteration":218,"passed_time":0.5367117222,"remaining_time":1.914026735},
{"learn":[0.9556595057],"iteration":219,"passed_time":0.538893791,"remaining_time":1.910623441},
{"learn":[0.9549530755],"iteration":220,"passed_time":0.5411134012,"remaining_time":1.907363527},
{"learn":[0.9541749175],"iteration":221,"passed_time":0.5436463427,"remaining_time":1.905211057},
{"learn":[0.9532217595],"iteration":222,"passed_time":0.5461465761,"remaining_time":1.902941209},
{"learn":[0.9521876889],"iteration":223,"passed_time":0.5486907675,"remaining_time":1.900821587},
{"learn":[0.9516259181],"iteration":224,"passed_time":0.5511439178,"remaining_time":1.898384606},
{"learn":[0.9505178543],"iteration":225,"passed_time":0.5534380692,"remaining_time":1.895402945},
{"learn":[0.9496293417],"iteration":226,"passed_time":0.5562031759,"remaining_time":1.894031079},
{"learn":[0.9486421526],"iteration":227,"passed_time":0.5585734934,"remaining_time":1.89131025},
{"learn":[0.9475025806],"iteration":228,"passed_time":0.5611631845,"remaining_time":1.889331071},
{"learn":[0.9467055624],"iteration":229,"passed_time":0.5636364181,"remaining_time":1.886956704},
{"learn":[0.9460018383],"iteration":230,"passed_time":0.5660081106,"remaining_time":1.884243451},
{"learn":[0.945561531],"iteration":231,"passed_time":0.568409428,"remaining_time":1.88163121},
{"learn":[0.9448568809],"iteration":232,"passed_time":0.5710744936,"remaining_time":1.879888998},
{"learn":[0.9440476626],"iteration":233,"passed_time":0.5734115197,"remaining_time":1.87706506},
{"learn":[0.9427716506],"iteration":234,"passed_time":0.5757205461,"remaining_time":1.874154118},
{"learn":[0.9421357759],"iteration":235,"passed_time":0.57813653,"remaining_time":1.871594529},
{"learn":[0.9414191521],"iteration":236,"passed_time":0.5806947213,"remaining_time":1.869493976},
{"learn":[0.9404602744],"iteration":237,"passed_time":0.5832569543,"remaining_time":1.867402517},
{"learn":[0.937043929],"iteration":238,"passed_time":0.5858883951,"remaining_time":1.865527484},
{"learn":[0.9363284415],"iteration":239,"passed_time":0.5881275469,"remaining_time":1.862403898},
{"learn":[0.9346484656],"iteration":240,"passed_time":0.5904282399,"remaining_time":1.859481469},
{"learn":[0.9339270633],"iteration":241,"passed_time":0.5929589314,"remaining_time":1.857284587},
{"learn":[0.9333757794],"iteration":242,"passed_time":0.5952321663,"remaining_time":1.854282921},
{"learn":[0.9322858666],"iteration":243,"passed_time":0.5978600238,"remaining_time":1.852385975},
{"learn":[0.9295947949],"iteration":244,"passed_time":0.6008637122,"remaining_time":1.851641235},
{"learn":[0.9288939011],"iteration":245,"passed_time":0.6033268208,"remaining_time":1.849221231},
{"learn":[0.9278989778],"iteration":246,"passed_time":0.6063866754,"remaining_time":1.848620108},
{"learn":[0.926776984],"iteration":247,"passed_time":0.6088136176,"remaining_time":1.846080002},
{"learn":[0.9231894346],"iteration":248,"passed_time":0.6111506021,"remaining_time":1.843269487},
{"learn":[0.92149055],"iteration":249,"passed_time":0.6135682943,"remaining_time":1.840704883},
{"learn":[0.9204552693],"iteration":250,"passed_time":0.6159301536,"remaining_time":1.837974841},
{"learn":[0.9180382124],"iteration":251,"passed_time":0.6182105968,"remaining_time":1.835006057},
{"learn":[0.9173060653],"iteration":252,"passed_time":0.6208359127,"remaining_time":1.833060975},
{"learn":[0.9164088149],"iteration":253,"passed_time":0.6232892714,"remaining_time":1.830605498},
{"learn":[0.9154667122],"iteration":254,"passed_time":0.6257427134,"remaining_time":1.82815028},
{"learn":[0.9143223998],"iteration":255,"passed_time":0.6280616979,"remaining_time":1.82530431},
{"learn":[0.9136791706],"iteration":256,"passed_time":0.6303511827,"remaining_time":1.822377155},
{"learn":[0.9127989747],"iteration":257,"passed_time":0.6327537917,"remaining_time":1.819780285},
{"learn":[0.9116860693],"iteration":258,"passed_time":0.6354924819,"remaining_time":1.818146444},
{"learn":[0.9111617804],"iteration":259,"passed_time":0.6380990479,"remaining_time":1.816128059},
{"learn":[0.9101938122],"iteration":260,"passed_time":0.6407122388,"remaining_time":1.814123925},
{"learn":[0.9092049264],"iteration":261,"passed_time":0.6430174735,"remaining_time":1.811247692},
{"learn":[0.9088253295],"iteration":262,"passed_time":0.6453529163,"remaining_time":1.808460454},
{"learn":[0.9079855171],"iteration":263,"passed_time":0.6479206492,"remaining_time":1.806324234},
{"learn":[0.9075100475],"iteration":264,"passed_time":0.6502828418,"remaining_time":1.803614675},
{"learn":[0.9067394532],"iteration":265,"passed_time":0.6528935745,"remaining_time":1.801593548},
{"learn":[0.9030601894],"iteration":266,"passed_time":0.6553141834,"remaining_time":1.799046054},
{"learn":[0.9026613205],"iteration":267,"passed_time":0.6577406256,"remaining_time":1.79651544},
{"learn":[0.9023545087],"iteration":268,"passed_time":0.6602995252,"remaining_time":1.79434555},
{"learn":[0.9014334881],"iteration":269,"passed_time":0.66259026,"remaining_time":1.79144774},
{"learn":[0.9008818756],"iteration":270,"passed_time":0.6653552416,"remaining_time":1.789830152},
{"learn":[0.8996007118],"iteration":271,"passed_time":0.6679185995,"remaining_time":1.787664487},
{"learn":[0.8987255455],"iteration":272,"passed_time":0.6702636256,"remaining_time":1.78491449},
{"learn":[0.897806633],"iteration":273,"passed_time":0.6729366912,"remaining_time":1.783036634},
{"learn":[0.8948801743],"iteration":274,"passed_time":0.6753375919,"remaining_time":1.780435469},
{"learn":[0.8940721025],"iteration":275,"passed_time":0.6777552841,"remaining_time":1.777879803},
{"learn":[0.8919063664],"iteration":276,"passed_time":0.6800360189,"remaining_time":1.77496766},
{"learn":[0.8909366612],"iteration":277,"passed_time":0.6827580425,"remaining_time":1.773206139},
{"learn":[0.8902723936],"iteration":278,"passed_time":0.6850934853,"remaining_time":1.77043872},
{"learn":[0.8888229592],"iteration":279,"passed_time":0.6874661362,"remaining_time":1.767770065},
{"learn":[0.8873269603],"iteration":280,"passed_time":0.6899514947,"remaining_time":1.765391903},
{"learn":[0.8865762845],"iteration":281,"passed_time":0.6921656883,"remaining_time":1.762322568},
{"learn":[0.8860916088],"iteration":282,"passed_time":0.6947530461,"remaining_time":1.760204714},
{"learn":[0.8842228565],"iteration":283,"passed_time":0.6971594051,"remaining_time":1.757627232},
{"learn":[0.8826783031],"iteration":284,"passed_time":0.6993961819,"remaining_time":1.754625509},
{"learn":[0.8820392866],"iteration":285,"passed_time":0.7017585828,"remaining_time":1.751942756},
{"learn":[0.881156201],"iteration":286,"passed_time":0.7042390663,"remaining_time":1.74955559},
{"learn":[0.8802230366],"iteration":287,"passed_time":0.7066847167,"remaining_time":1.747081661},
{"learn":[0.8788471924],"iteration":288,"passed_time":0.7091434504,"remaining_time":1.744640115},
{"learn":[0.8783337084],"iteration":289,"passed_time":0.7116806835,"remaining_time":1.742390639},
{"learn":[0.8776896563],"iteration":290,"passed_time":0.7142124583,"remaining_time":1.740125886},
{"learn":[0.8772868982],"iteration":291,"passed_time":0.716512693,"remaining_time":1.7372979},
{"learn":[0.8770401278],"iteration":292,"passed_time":0.7190279263,"remaining_time":1.7349923},
{"learn":[0.8762481078],"iteration":293,"passed_time":0.7216129091,"remaining_time":1.732852768},
{"learn":[0.875797243],"iteration":294,"passed_time":0.7240310597,"remaining_time":1.730311516},
{"learn":[0.8736548313],"iteration":295,"passed_time":0.726594501,"remaining_time":1.728116651},
{"learn":[0.8729945038],"iteration":296,"passed_time":0.7290806094,"remaining_time":1.725736257},
{"learn":[0.8722218879],"iteration":297,"passed_time":0.7317614666,"remaining_time":1.723813925},
{"learn":[0.871058303],"iteration":298,"passed_time":0.7343224079,"remaining_time":1.721605378},
{"learn":[0.8682332749],"iteration":299,"passed_time":0.7368346412,"remaining_time":1.719280829},
{"learn":[0.8673136208],"iteration":300,"passed_time":0.7394874986,"remaining_time":1.7172816},
{"learn":[0.8659861011],"iteration":301,"passed_time":0.7418000665,"remaining_time":1.714491544},
{"learn":[0.8653687779],"iteration":302,"passed_time":0.7446535892,"remaining_time":1.712949015},
{"learn":[0.8648064271],"iteration":303,"passed_time":0.7472347387,"remaining_time":1.71077427},
{"learn":[0.8641900407],"iteration":304,"passed_time":0.7502644269,"remaining_time":1.70961894},
{"learn":[0.8635247104],"iteration":305,"passed_time":0.7528100766,"remaining_time":1.707353572},
{"learn":[0.8609943489],"iteration":306,"passed_time":0.7551248946,"remaining_time":1.704565316},
{"learn":[0.8605864824],"iteration":307,"passed_time":0.7574835039,"remaining_time":1.701878522},
{"learn":[0.8591538586],"iteration":308,"passed_time":0.7596603644,"remaining_time":1.698787417},
{"learn":[0.8587686304],"iteration":309,"passed_time":0.7621423479,"remaining_time":1.696381355},
{"learn":[0.8580547693],"iteration":310,"passed_time":0.7646988309,"remaining_time":1.694139854},
{"learn":[0.857302614],"iteration":311,"passed_time":0.7671701061,"remaining_time":1.691708439},
{"learn":[0.8551622381],"iteration":312,"passed_time":0.7695697152,"remaining_time":1.689119471},
{"learn":[0.8546519131],"iteration":313,"passed_time":0.7720829484,"remaining_time":1.686779945},
{"learn":[0.8540528367],"iteration":314,"passed_time":0.7744067663,"remaining_time":1.684027412},
{"learn":[0.8533671261],"iteration":315,"passed_time":0.7768228336,"remaining_time":1.681477273},
{"learn":[0.8530957008],"iteration":316,"passed_time":0.7790813186,"remaining_time":1.678588456},
{"learn":[0.8522641921],"iteration":317,"passed_time":0.7815576771,"remaining_time":1.676170867},
{"learn":[0.849746522],"iteration":318,"passed_time":0.7841242434,"remaining_time":1.673945485},
{"learn":[0.8491962107],"iteration":319,"passed_time":0.7867879756,"remaining_time":1.671924448},
{"learn":[0.8467577798],"iteration":320,"passed_time":0.789243376,"remaining_time":1.66945873},
{"learn":[0.8459105039],"iteration":321,"passed_time":0.7920001076,"remaining_time":1.667627556},
{"learn":[0.844324461],"iteration":322,"passed_time":0.7944783828,"remaining_time":1.665207013},
{"learn":[0.8438851504],"iteration":323,"passed_time":0.7967309095,"remaining_time":1.662315107},
{"learn":[0.8429164133],"iteration":324,"passed_time":0.7993299756,"remaining_time":1.660146872},
{"learn":[0.8423945384],"iteration":325,"passed_time":0.8021062904,"remaining_time":1.658342453},
{"learn":[0.8421113401],"iteration":326,"passed_time":0.8046147737,"remaining_time":1.655980865},
{"learn":[0.8418197576],"iteration":327,"passed_time":0.8070720491,"remaining_time":1.653513466},
{"learn":[0.841509819],"iteration":328,"passed_time":0.8094546582,"remaining_time":1.650893847},
{"learn":[0.8411450115],"iteration":329,"passed_time":0.8120876407,"remaining_time":1.648783998},
{"learn":[0.8405788094],"iteration":330,"passed_time":0.8144933747,"remaining_time":1.646211685},
{"learn":[0.840307441],"iteration":331,"passed_time":0.8169309835,"remaining_time":1.643704509},
{"learn":[0.8389718164],"iteration":332,"passed_time":0.8191918018,"remaining_time":1.640843639},
{"learn":[0.8382269916],"iteration":333,"passed_time":0.8216924102,"remaining_time":1.638464506},
{"learn":[0.8375686241],"iteration":334,"passed_time":0.8242360182,"remaining_time":1.636170006},
{"learn":[0.836652776],"iteration":335,"passed_time":0.8266745854,"remaining_time":1.633666443},
{"learn":[0.8350786603],"iteration":336,"passed_time":0.8290750694,"remaining_time":1.631088341},
{"learn":[0.8344447467],"iteration":337,"passed_time":0.8317675098,"remaining_time":1.629083111},
{"learn":[0.8339783908],"iteration":338,"passed_time":0.8342474517,"remaining_time":1.626659485},
{"learn":[0.8332603836],"iteration":339,"passed_time":0.8369967667,"remaining_time":1.62475843},
{"learn":[0.8329107038],"iteration":340,"passed_time":0.8394567087,"remaining_time":1.62229317},
{"learn":[0.8312142377],"iteration":341,"passed_time":0.841812818,"remaining_time":1.61962817},
{"learn":[0.8309754176],"iteration":342,"passed_time":0.844115886,"remaining_time":1.616863374},
{"learn":[0.8303164608],"iteration":343,"passed_time":0.8467490352,"remaining_time":1.614730718},
{"learn":[0.830004969],"iteration":344,"passed_time":0.8494451006,"remaining_time":1.612714611},
{"learn":[0.8295238015],"iteration":345,"passed_time":0.8521186661,"remaining_time":1.610652045},
{"learn":[0.8289915036],"iteration":346,"passed_time":0.8545621916,"remaining_time":1.608153058},
{"learn":[0.8277047506],"iteration":347,"passed_time":0.856858218,"remaining_time":1.605378041},
{"learn":[0.8256345216],"iteration":348,"passed_time":0.8591889941,"remaining_time":1.602670588},
{"learn":[0.8251869984],"iteration":349,"passed_time":0.861408396,"remaining_time":1.59975845},
{"learn":[0.8246041833],"iteration":350,"passed_time":0.8638069634,"remaining_time":1.597181536},
{"learn":[0.8241612746],"iteration":351,"passed_time":0.8664652791,"remaining_time":1.595083809},
{"learn":[0.8223234615],"iteration":352,"passed_time":0.8687653054,"remaining_time":1.592326211},
{"learn":[0.821991074],"iteration":353,"passed_time":0.8711137065,"remaining_time":1.589659476},
{"learn":[0.8215097285],"iteration":354,"passed_time":0.8735520653,"remaining_time":1.587157978},
{"learn":[0.8211121857],"iteration":355,"passed_time":0.8759665492,"remaining_time":1.584613645},
{"learn":[0.8204060638],"iteration":356,"passed_time":0.8787281558,"remaining_time":1.58269525},
{"learn":[0.820030488],"iteration":357,"passed_time":0.8812018061,"remaining_time":1.580255753},
{"learn":[0.8195404763],"iteration":358,"passed_time":0.8837994138,"remaining_time":1.578037393},
{"learn":[0.8191119895],"iteration":359,"passed_time":0.8862731473,"remaining_time":1.575596706},
{"learn":[0.818857945],"iteration":360,"passed_time":0.8888495052,"remaining_time":1.57333749},
{"learn":[0.818368598],"iteration":361,"passed_time":0.8915609872,"remaining_time":1.571314668},
{"learn":[0.8174700279],"iteration":362,"passed_time":0.8940945953,"remaining_time":1.568975915},
{"learn":[0.8170073966],"iteration":363,"passed_time":0.8966189952,"remaining_time":1.566620003},
{"learn":[0.8150373334],"iteration":364,"passed_time":0.8989889794,"remaining_time":1.563994526},
{"learn":[0.8147973551],"iteration":365,"passed_time":0.9013197556,"remaining_time":1.561302527},
{"learn":[0.8143538541],"iteration":366,"passed_time":0.9037878225,"remaining_time":1.558849296},
{"learn":[0.8140601087],"iteration":367,"passed_time":0.9065067211,"remaining_time":1.55682676},
{"learn":[0.8136197662],"iteration":368,"passed_time":0.9089920796,"remaining_time":1.55440109},
{"learn":[0.8133949077],"iteration":369,"passed_time":0.91117994,"remaining_time":1.551468547},
{"learn":[0.8130174111],"iteration":370,"passed_time":0.9138716304,"remaining_time":1.54939422},
{"learn":[0.8120119349],"iteration":371,"passed_time":0.9161222405,"remaining_time":1.546571954},
{"learn":[0.8116883856],"iteration":372,"passed_time":0.918692265,"remaining_time":1.544289679},
{"learn":[0.8114369762],"iteration":373,"passed_time":0.9211453321,"remaining_time":1.541810101},
{"learn":[0.8112033003],"iteration":374,"passed_time":0.9238755222,"remaining_time":1.539792537},
{"learn":[0.8095769647],"iteration":375,"passed_time":0.9262360065,"remaining_time":1.537157628},
{"learn":[0.8089364013],"iteration":376,"passed_time":0.9288144061,"remaining_time":1.534884284},
{"learn":[0.8085767924],"iteration":377,"passed_time":0.9312054318,"remaining_time":1.532301002},
{"learn":[0.8082990426],"iteration":378,"passed_time":0.9335382496,"remaining_time":1.529623359},
{"learn":[0.8078858212],"iteration":379,"passed_time":0.9364733968,"remaining_time":1.527930279},
{"learn":[0.8060214454],"iteration":380,"passed_time":0.9391907537,"remaining_time":1.525876841},
{"learn":[0.8055827654],"iteration":381,"passed_time":0.9417782782,"remaining_time":1.523609885},
{"learn":[0.8051503479],"iteration":382,"passed_time":0.9445523014,"remaining_time":1.521641697},
{"learn":[0.8047062785],"iteration":383,"passed_time":0.9469578687,"remaining_time":1.519078248},
{"learn":[0.8042371523],"iteration":384,"passed_time":0.9493614361,"remaining_time":1.516512424},
{"learn":[0.8038400821],"iteration":385,"passed_time":0.9517516285,"remaining_time":1.513926166},
{"learn":[0.8035663529],"iteration":386,"passed_time":0.9544566939,"remaining_time":1.511839673},
{"learn":[0.8026292627],"iteration":387,"passed_time":0.9570703431,"remaining_time":1.509605799},
{"learn":[0.8022997975],"iteration":388,"passed_time":0.9596547426,"remaining_time":1.50732403},
{"learn":[0.8020987712],"iteration":389,"passed_time":0.9621854758,"remaining_time":1.50495677},
{"learn":[0.801774857],"iteration":390,"passed_time":0.9644743772,"remaining_time":1.50221201},
{"learn":[0.8013691544],"iteration":391,"passed_time":0.9670437351,"remaining_time":1.499904569},
{"learn":[0.8005492269],"iteration":392,"passed_time":0.9691855959,"remaining_time":1.496935513},
{"learn":[0.7982115509],"iteration":393,"passed_time":0.9715515802,"remaining_time":1.494315375},
{"learn":[0.7977006555],"iteration":394,"passed_time":0.9738970646,"remaining_time":1.491665124},
{"learn":[0.7972026412],"iteration":395,"passed_time":0.9764446726,"remaining_time":1.489324703},
{"learn":[0.7967900358],"iteration":396,"passed_time":0.9792742371,"remaining_time":1.487411499},
{"learn":[0.7963475228],"iteration":397,"passed_time":0.9820045523,"remaining_time":1.485343569},
{"learn":[0.7960837287],"iteration":398,"passed_time":0.9848115753,"remaining_time":1.483387862},
{"learn":[0.7958128352],"iteration":399,"passed_time":0.9876731396,"remaining_time":1.481509709},
{"learn":[0.7954841993],"iteration":400,"passed_time":0.9903897882,"remaining_time":1.479410182},
{"learn":[0.7952739157],"iteration":401,"passed_time":0.9930155207,"remaining_time":1.477172342},
{"learn":[0.7949846139],"iteration":402,"passed_time":0.9957985856,"remaining_time":1.475165647},
{"learn":[0.7945322992],"iteration":403,"passed_time":0.9983916517,"remaining_time":1.472874813},
{"learn":[0.7940164459],"iteration":404,"passed_time":1.000911885,"remaining_time":1.470475485},
{"learn":[0.7936690053],"iteration":405,"passed_time":1.003497951,"remaining_time":1.468171879},
{"learn":[0.7932916577],"iteration":406,"passed_time":1.006230058,"remaining_time":1.466079667},
{"learn":[0.7929779845],"iteration":407,"passed_time":1.008517834,"remaining_time":1.463339603},
{"learn":[0.791600713],"iteration":408,"passed_time":1.010959776,"remaining_time":1.460824518},
{"learn":[0.7911861122],"iteration":409,"passed_time":1.013589551,"remaining_time":1.458580085},
{"learn":[0.790881211],"iteration":410,"passed_time":1.016057451,"remaining_time":1.456101797},
{"learn":[0.7905952148],"iteration":411,"passed_time":1.018529476,"remaining_time":1.453629446},
{"learn":[0.7903689816],"iteration":412,"passed_time":1.020846377,"remaining_time":1.450936619},
{"learn":[0.7902184365],"iteration":413,"passed_time":1.023098862,"remaining_time":1.448154428},
{"learn":[0.7899956148],"iteration":414,"passed_time":1.025374264,"remaining_time":1.445407095},
{"learn":[0.7885809372],"iteration":415,"passed_time":1.027883956,"remaining_time":1.442990938},
{"learn":[0.7882074122],"iteration":416,"passed_time":1.030766061,"remaining_time":1.441094997},
{"learn":[0.7880176699],"iteration":417,"passed_time":1.033235337,"remaining_time":1.438619536},
{"learn":[0.7878421299],"iteration":418,"passed_time":1.035609071,"remaining_time":1.436011623},
{"learn":[0.7875089914],"iteration":419,"passed_time":1.037934055,"remaining_time":1.433337505},
{"learn":[0.7873528149],"iteration":420,"passed_time":1.040333373,"remaining_time":1.430767275},
{"learn":[0.7869742701],"iteration":421,"passed_time":1.04303423,"remaining_time":1.428610864},
{"learn":[0.7863534262],"iteration":422,"passed_time":1.045628088,"remaining_time":1.426305926},
{"learn":[0.7860531601],"iteration":423,"passed_time":1.048165404,"remaining_time":1.423922813},
{"learn":[0.7856267091],"iteration":424,"passed_time":1.050689721,"remaining_time":1.421521387},
{"learn":[0.785305747],"iteration":425,"passed_time":1.053266078,"remaining_time":1.419189505},
{"learn":[0.7850419208],"iteration":426,"passed_time":1.055960685,"remaining_time":1.417015159},
{"learn":[0.7847819659],"iteration":427,"passed_time":1.058513752,"remaining_time":1.41464922},
{"learn":[0.7845058077],"iteration":428,"passed_time":1.061108693,"remaining_time":1.412338144},
{"learn":[0.783112154],"iteration":429,"passed_time":1.063492594,"remaining_time":1.409745996},
{"learn":[0.7829136597],"iteration":430,"passed_time":1.065995994,"remaining_time":1.407312576},
{"learn":[0.7811589355],"iteration":431,"passed_time":1.068731392,"remaining_time":1.405183867},
{"learn":[0.7809329285],"iteration":432,"passed_time":1.070860961,"remaining_time":1.402259042},
{"learn":[0.7806587364],"iteration":433,"passed_time":1.07327282,"remaining_time":1.399706028},
{"learn":[0.7804957783],"iteration":434,"passed_time":1.075635471,"remaining_time":1.39708975},
{"learn":[0.7803700731],"iteration":435,"passed_time":1.07801233,"remaining_time":1.394493015},
{"learn":[0.7800534777],"iteration":436,"passed_time":1.080800479,"remaining_time":1.392427161},
{"learn":[0.7798004735],"iteration":437,"passed_time":1.083275212,"remaining_time":1.389955866},
{"learn":[0.7789526042],"iteration":438,"passed_time":1.085705321,"remaining_time":1.387427529},
{"learn":[0.7785953108],"iteration":439,"passed_time":1.08829697,"remaining_time":1.385105235},
{"learn":[0.7784388139],"iteration":440,"passed_time":1.090837245,"remaining_time":1.382716599},
{"learn":[0.7780495879],"iteration":441,"passed_time":1.093362562,"remaining_time":1.380308392},
{"learn":[0.7771815755],"iteration":442,"passed_time":1.095878795,"remaining_time":1.377888237},
{"learn":[0.7769683359],"iteration":443,"passed_time":1.09856811,"remaining_time":1.375684391},
{"learn":[0.7766144161],"iteration":444,"passed_time":1.101018052,"remaining_time":1.373179818},
{"learn":[0.7763718846],"iteration":445,"passed_time":1.10361941,"remaining_time":1.370863572},
{"learn":[0.7757850981],"iteration":446,"passed_time":1.106228809,"remaining_time":1.368555999},
{"learn":[0.7754401926],"iteration":447,"passed_time":1.10917029,"remaining_time":1.36665625},
{"learn":[0.7751363197],"iteration":448,"passed_time":1.111813356,"remaining_time":1.364385655},
{"learn":[0.7747847572],"iteration":449,"passed_time":1.114769711,"remaining_time":1.362496313},
{"learn":[0.7738033747],"iteration":450,"passed_time":1.117177862,"remaining_time":1.359934914},
{"learn":[0.7734921971],"iteration":451,"passed_time":1.119760261,"remaining_time":1.357585449},
{"learn":[0.7728828077],"iteration":452,"passed_time":1.12225437,"remaining_time":1.355128345},
{"learn":[0.7727175133],"iteration":453,"passed_time":1.124539313,"remaining_time":1.352419526},
{"learn":[0.7724324946],"iteration":454,"passed_time":1.126981505,"remaining_time":1.349900923},
{"learn":[0.7722443185],"iteration":455,"passed_time":1.129216907,"remaining_time":1.347135959},
{"learn":[0.7719202526],"iteration":456,"passed_time":1.131892597,"remaining_time":1.344896456},
{"learn":[0.7708919672],"iteration":457,"passed_time":1.134320664,"remaining_time":1.342362009},
{"learn":[0.7698791158],"iteration":458,"passed_time":1.136922064,"remaining_time":1.340032323},
{"learn":[0.7677720224],"iteration":459,"passed_time":1.139477213,"remaining_time":1.337647163},
{"learn":[0.7669471259],"iteration":460,"passed_time":1.141822156,"remaining_time":1.335015493},
{"learn":[0.7656106108],"iteration":461,"passed_time":1.144122266,"remaining_time":1.332332855},
{"learn":[0.7653430032],"iteration":462,"passed_time":1.14693958,"remaining_time":1.330251738},
{"learn":[0.765021051],"iteration":463,"passed_time":1.149499772,"remaining_time":1.327870426},
{"learn":[0.7647118828],"iteration":464,"passed_time":1.151929797,"remaining_time":1.325338584},
{"learn":[0.7646173479],"iteration":465,"passed_time":1.154099824,"remaining_time":1.322509241},
{"learn":[0.7644335835],"iteration":466,"passed_time":1.156564141,"remaining_time":1.320018602},
{"learn":[0.7640928384],"iteration":467,"passed_time":1.159240165,"remaining_time":1.317768735},
{"learn":[0.7637662126],"iteration":468,"passed_time":1.161774232,"remaining_time":1.315356326},
{"learn":[0.7634419705],"iteration":469,"passed_time":1.164337131,"remaining_time":1.312975914},
{"learn":[0.7630567669],"iteration":470,"passed_time":1.166823698,"remaining_time":1.310508994},
{"learn":[0.7628335628],"iteration":471,"passed_time":1.169298432,"remaining_time":1.308028754},
{"learn":[0.7614728348],"iteration":472,"passed_time":1.171776415,"remaining_time":1.305552158},
{"learn":[0.7606232262],"iteration":473,"passed_time":1.174174983,"remaining_time":1.302987428},
{"learn":[0.7603321375],"iteration":474,"passed_time":1.176622716,"remaining_time":1.300477739},
{"learn":[0.7600463697],"iteration":475,"passed_time":1.179046825,"remaining_time":1.297942303},
{"learn":[0.758606888],"iteration":476,"passed_time":1.181482601,"remaining_time":1.295420126},
{"learn":[0.7582416982],"iteration":477,"passed_time":1.184112833,"remaining_time":1.293110667},
{"learn":[0.7566992608],"iteration":478,"passed_time":1.186471776,"remaining_time":1.290504792},
{"learn":[0.7563594432],"iteration":479,"passed_time":1.189087675,"remaining_time":1.288178315},
{"learn":[0.7561294667],"iteration":480,"passed_time":1.1915807,"remaining_time":1.285718053},
{"learn":[0.755617102],"iteration":481,"passed_time":1.194092475,"remaining_time":1.283277805},
{"learn":[0.7552885468],"iteration":482,"passed_time":1.196389501,"remaining_time":1.280607396},
{"learn":[0.7550452334],"iteration":483,"passed_time":1.198897318,"remaining_time":1.278163257},
{"learn":[0.7547691595],"iteration":484,"passed_time":1.201664925,"remaining_time":1.275994714},
{"learn":[0.7544059043],"iteration":485,"passed_time":1.204102825,"remaining_time":1.273475004},
{"learn":[0.7531082216],"iteration":486,"passed_time":1.206493601,"remaining_time":1.27090599},
{"learn":[0.7528062375],"iteration":487,"passed_time":1.2091615,"remaining_time":1.268628459},
{"learn":[0.7514859365],"iteration":488,"passed_time":1.211449985,"remaining_time":1.265952847},
{"learn":[0.7511670675],"iteration":489,"passed_time":1.213734553,"remaining_time":1.263274739},
{"learn":[0.7508820198],"iteration":490,"passed_time":1.216303161,"remaining_time":1.260892686},
{"learn":[0.7507487233],"iteration":491,"passed_time":1.218559437,"remaining_time":1.258187387},
{"learn":[0.7500617397],"iteration":492,"passed_time":1.220936922,"remaining_time":1.255608558},
{"learn":[0.7498102677],"iteration":493,"passed_time":1.223728903,"remaining_time":1.253455111},
{"learn":[0.7495337347],"iteration":494,"passed_time":1.227091047,"remaining_time":1.251880765},
{"learn":[0.7491699885],"iteration":495,"passed_time":1.229773238,"remaining_time":1.24960829},
{"learn":[0.7488331906],"iteration":496,"passed_time":1.232299888,"remaining_time":1.247176747},
{"learn":[0.7486042095],"iteration":497,"passed_time":1.235055578,"remaining_time":1.244975703},
{"learn":[0.7483560925],"iteration":498,"passed_time":1.237689393,"remaining_time":1.242650072},
{"learn":[0.7481399563],"iteration":499,"passed_time":1.240222002,"remaining_time":1.240222002},
{"learn":[0.7478855052],"iteration":500,"passed_time":1.242932942,"remaining_time":1.237971134},
{"learn":[0.7476309695],"iteration":501,"passed_time":1.245367342,"remaining_time":1.235444097},
{"learn":[0.7474911596],"iteration":502,"passed_time":1.247653494,"remaining_time":1.232770947},
{"learn":[0.7472010175],"iteration":503,"passed_time":1.250249685,"remaining_time":1.230404452},
{"learn":[0.7459916895],"iteration":504,"passed_time":1.252780668,"remaining_time":1.22797313},
{"learn":[0.7444113468],"iteration":505,"passed_time":1.255921647,"remaining_time":1.226136944},
{"learn":[0.7442142667],"iteration":506,"passed_time":1.258293548,"remaining_time":1.22354777},
{"learn":[0.7439860983],"iteration":507,"passed_time":1.260951905,"remaining_time":1.221236885},
{"learn":[0.7437049012],"iteration":508,"passed_time":1.26327139,"remaining_time":1.218597746},
{"learn":[0.7429085964],"iteration":509,"passed_time":1.265695041,"remaining_time":1.216059941},
{"learn":[0.7422799586],"iteration":510,"passed_time":1.267980942,"remaining_time":1.213390764},
{"learn":[0.7418823606],"iteration":511,"passed_time":1.270628466,"remaining_time":1.211067757},
{"learn":[0.7415851598],"iteration":512,"passed_time":1.273439864,"remaining_time":1.208899052},
{"learn":[0.7409540919],"iteration":513,"passed_time":1.275861765,"remaining_time":1.206359567},
{"learn":[0.7406627001],"iteration":514,"passed_time":1.278425623,"remaining_time":1.203954227},
{"learn":[0.7405575203],"iteration":515,"passed_time":1.28075219,"remaining_time":1.201325698},
{"learn":[0.7402490102],"iteration":516,"passed_time":1.283567338,"remaining_time":1.199154786},
{"learn":[0.7399309239],"iteration":517,"passed_time":1.286022864,"remaining_time":1.196646757},
{"learn":[0.739518864],"iteration":518,"passed_time":1.288553805,"remaining_time":1.194208825},
{"learn":[0.7393223475],"iteration":519,"passed_time":1.291014247,"remaining_time":1.191705459},
{"learn":[0.7389505318],"iteration":520,"passed_time":1.293385148,"remaining_time":1.189119935},
{"learn":[0.738677],"iteration":521,"passed_time":1.296365837,"remaining_time":1.18709362},
{"learn":[0.738311911],"iteration":522,"passed_time":1.299108735,"remaining_time":1.184846781},
{"learn":[0.738193954],"iteration":523,"passed_time":1.301560552,"remaining_time":1.182333631},
{"learn":[0.7378997572],"iteration":524,"passed_time":1.303973119,"remaining_time":1.179785203},
{"learn":[0.7374968742],"iteration":525,"passed_time":1.306888558,"remaining_time":1.17769045},
{"learn":[0.7371734091],"iteration":526,"passed_time":1.309273709,"remaining_time":1.175116631},
{"learn":[0.73659684],"iteration":527,"passed_time":1.311639402,"remaining_time":1.172526132},
{"learn":[0.7364100339],"iteration":528,"passed_time":1.314201968,"remaining_time":1.170111771},
{"learn":[0.7362111846],"iteration":529,"passed_time":1.317374405,"remaining_time":1.16823768},
{"learn":[0.7360024813],"iteration":530,"passed_time":1.320232011,"remaining_time":1.166080628},
{"learn":[0.7352633832],"iteration":531,"passed_time":1.323030784,"remaining_time":1.163869186},
{"learn":[0.7350921331],"iteration":532,"passed_time":1.32544706,"remaining_time":1.161320407},
{"learn":[0.7341038791],"iteration":533,"passed_time":1.327801836,"remaining_time":1.158718456},
{"learn":[0.7337665177],"iteration":534,"passed_time":1.330564817,"remaining_time":1.156472225},
{"learn":[0.7334671794],"iteration":535,"passed_time":1.333129925,"remaining_time":1.154052771},
{"learn":[0.7333565281],"iteration":536,"passed_time":1.335512243,"remaining_time":1.151475174},
{"learn":[0.7327827139],"iteration":537,"passed_time":1.338037059,"remaining_time":1.149020672},
{"learn":[0.7326130465],"iteration":538,"passed_time":1.340555001,"remaining_time":1.146560029},
{"learn":[0.7319971983],"iteration":539,"passed_time":1.342829903,"remaining_time":1.143892139},
{"learn":[0.7316994265],"iteration":540,"passed_time":1.345520926,"remaining_time":1.141578753},
{"learn":[0.7314833653],"iteration":541,"passed_time":1.347770078,"remaining_time":1.138890583},
{"learn":[0.7311741842],"iteration":542,"passed_time":1.350385686,"remaining_time":1.136512446},
{"learn":[0.7310262276],"iteration":543,"passed_time":1.353040501,"remaining_time":1.134166303},
{"learn":[0.7307549414],"iteration":544,"passed_time":1.355649401,"remaining_time":1.131780692},
{"learn":[0.7305821947],"iteration":545,"passed_time":1.358052135,"remaining_time":1.129222837},
{"learn":[0.7303118685],"iteration":546,"passed_time":1.360482327,"remaining_time":1.126688289},
{"learn":[0.7301424482],"iteration":547,"passed_time":1.363488307,"remaining_time":1.124629041},
{"learn":[0.7290198804],"iteration":548,"passed_time":1.365748542,"remaining_time":1.12195372},
{"learn":[0.7287457567],"iteration":549,"passed_time":1.368519273,"remaining_time":1.119697587},
{"learn":[0.7284920191],"iteration":550,"passed_time":1.371484754,"remaining_time":1.117598284},
{"learn":[0.7282529521],"iteration":551,"passed_time":1.374201569,"remaining_time":1.115294027},
{"learn":[0.7280637024],"iteration":552,"passed_time":1.376583511,"remaining_time":1.112717594},
{"learn":[0.7278594194],"iteration":553,"passed_time":1.379032078,"remaining_time":1.1101955},
{"learn":[0.7275273931],"iteration":554,"passed_time":1.381653061,"remaining_time":1.107811914},
{"learn":[0.7272920025],"iteration":555,"passed_time":1.384380793,"remaining_time":1.10551272},
{"learn":[0.7261405146],"iteration":556,"passed_time":1.387502272,"remaining_time":1.103525146},
{"learn":[0.725926164],"iteration":557,"passed_time":1.389882006,"remaining_time":1.100945962},
{"learn":[0.7256708672],"iteration":558,"passed_time":1.392424698,"remaining_time":1.09849605},
{"learn":[0.7252449232],"iteration":559,"passed_time":1.394712849,"remaining_time":1.09584581},
{"learn":[0.7251116793],"iteration":560,"passed_time":1.397254082,"remaining_time":1.093394906},
{"learn":[0.7248762844],"iteration":561,"passed_time":1.399755941,"remaining_time":1.090912993},
{"learn":[0.7247500156],"iteration":562,"passed_time":1.402456756,"remaining_time":1.088585439},
{"learn":[0.7233898178],"iteration":563,"passed_time":1.405107322,"remaining_time":1.086217717},
{"learn":[0.7230728052],"iteration":564,"passed_time":1.407719138,"remaining_time":1.083819159},
{"learn":[0.7228921244],"iteration":565,"passed_time":1.410335829,"remaining_time":1.081423586},
{"learn":[0.7227051903],"iteration":566,"passed_time":1.412765937,"remaining_time":1.078884746},
{"learn":[0.7224938774],"iteration":567,"passed_time":1.415484669,"remaining_time":1.076565805},
{"learn":[0.7222300836],"iteration":568,"passed_time":1.418114569,"remaining_time":1.074178171},
{"learn":[0.7219189244],"iteration":569,"passed_time":1.420570094,"remaining_time":1.071658141},
{"learn":[0.7217668419],"iteration":570,"passed_time":1.423150827,"remaining_time":1.069232407},
{"learn":[0.7216520351],"iteration":571,"passed_time":1.42544577,"remaining_time":1.066592289},
{"learn":[0.7204193515],"iteration":572,"passed_time":1.428019461,"remaining_time":1.064161099},
{"learn":[0.7202263949],"iteration":573,"passed_time":1.430479445,"remaining_time":1.061645023},
{"learn":[0.7200833077],"iteration":574,"passed_time":1.433087011,"remaining_time":1.059238225},
{"learn":[0.7198258454],"iteration":575,"passed_time":1.435801243,"remaining_time":1.056909248},
{"learn":[0.7195958559],"iteration":576,"passed_time":1.438332351,"remaining_time":1.054444687},
{"learn":[0.7187011924],"iteration":577,"passed_time":1.440898834,"remaining_time":1.052005723},
{"learn":[0.717853277],"iteration":578,"passed_time":1.443289443,"remaining_time":1.049438438},
{"learn":[0.7172086573],"iteration":579,"passed_time":1.445532553,"remaining_time":1.046764952},
{"learn":[0.7170138807],"iteration":580,"passed_time":1.448102036,"remaining_time":1.044328318},
{"learn":[0.7165844072],"iteration":581,"passed_time":1.450635394,"remaining_time":1.041865283},
{"learn":[0.7149332266],"iteration":582,"passed_time":1.45315721,"remaining_time":1.039393751},
{"learn":[0.7147796445],"iteration":583,"passed_time":1.455788776,"remaining_time":1.037000224},
{"learn":[0.7145806431],"iteration":584,"passed_time":1.458390842,"remaining_time":1.034584957},
{"learn":[0.7140255585],"iteration":585,"passed_time":1.461079241,"remaining_time":1.032230044},
{"learn":[0.7139002213],"iteration":586,"passed_time":1.463642432,"remaining_time":1.029785902},
{"learn":[0.7134636777],"iteration":587,"passed_time":1.465987667,"remaining_time":1.027188637},
{"learn":[0.7132578827],"iteration":588,"passed_time":1.468796523,"remaining_time":1.02491574},
{"learn":[0.713067634],"iteration":589,"passed_time":1.471452464,"remaining_time":1.022534763},
{"learn":[0.7115652576],"iteration":590,"passed_time":1.473821365,"remaining_time":1.01995421},
{"learn":[0.7114331021],"iteration":591,"passed_time":1.476498097,"remaining_time":1.017586526},
{"learn":[0.7106780138],"iteration":592,"passed_time":1.478905331,"remaining_time":1.015032833},
{"learn":[0.710556684],"iteration":593,"passed_time":1.481232607,"remaining_time":1.012424981},
{"learn":[0.7104077304],"iteration":594,"passed_time":1.483855923,"remaining_time":1.010019578},
{"learn":[0.7100079159],"iteration":595,"passed_time":1.486177991,"remaining_time":1.007409242},
{"learn":[0.7098769285],"iteration":596,"passed_time":1.488784599,"remaining_time":1.004991948},
{"learn":[0.7096369713],"iteration":597,"passed_time":1.491227124,"remaining_time":1.002463719},
{"learn":[0.709342225],"iteration":598,"passed_time":1.493538984,"remaining_time":0.9998483012},
{"learn":[0.7091398764],"iteration":599,"passed_time":1.496066675,"remaining_time":0.9973777834},
{"learn":[0.7089413427],"iteration":600,"passed_time":1.49835016,"remaining_time":0.9947449481},
{"learn":[0.7084700462],"iteration":601,"passed_time":1.500645936,"remaining_time":0.9921213998},
{"learn":[0.7082843718],"iteration":602,"passed_time":1.503055754,"remaining_time":0.9895740202},
{"learn":[0.7077637759],"iteration":603,"passed_time":1.50562882,"remaining_time":0.9871341269},
{"learn":[0.7076038298],"iteration":604,"passed_time":1.508194053,"remaining_time":0.9846886791},
{"learn":[0.7071093258],"iteration":605,"passed_time":1.510540954,"remaining_time":0.9821008842},
{"learn":[0.7068123235],"iteration":606,"passed_time":1.51281748,"remaining_time":0.9794683192},
{"learn":[0.7067041945],"iteration":607,"passed_time":1.515062799,"remaining_time":0.9768168045},
{"learn":[0.7062648833],"iteration":608,"passed_time":1.51757499,"remaining_time":0.9743379659},
{"learn":[0.7060737591],"iteration":609,"passed_time":1.520405805,"remaining_time":0.9720627277},
{"learn":[0.7056911421],"iteration":610,"passed_time":1.523021329,"remaining_time":0.969648604},
{"learn":[0.7055491663],"iteration":611,"passed_time":1.525299481,"remaining_time":0.9670199322},
{"learn":[0.7051865201],"iteration":612,"passed_time":1.527494883,"remaining_time":0.9643401625},
{"learn":[0.7047335412],"iteration":613,"passed_time":1.529915658,"remaining_time":0.9618036549},
{"learn":[0.7046353907],"iteration":614,"passed_time":1.532528933,"remaining_time":0.959388031},
{"learn":[0.7044559167],"iteration":615,"passed_time":1.53537058,"remaining_time":0.957114128},
{"learn":[0.7042630463],"iteration":616,"passed_time":1.538243686,"remaining_time":0.9548579122},
{"learn":[0.7037581754],"iteration":617,"passed_time":1.540885544,"remaining_time":0.95245676},
{"learn":[0.703380534],"iteration":618,"passed_time":1.543250486,"remaining_time":0.9498843866},
{"learn":[0.7032204939],"iteration":619,"passed_time":1.545937718,"remaining_time":0.9475102145},
{"learn":[0.703080109],"iteration":620,"passed_time":1.548392119,"remaining_time":0.9449929356},
{"learn":[0.70285963],"iteration":621,"passed_time":1.550839019,"remaining_time":0.942471301},
{"learn":[0.7026829483],"iteration":622,"passed_time":1.553370252,"remaining_time":0.9400009392},
{"learn":[0.7024253273],"iteration":623,"passed_time":1.555710195,"remaining_time":0.9374151176},
{"learn":[0.7013048956],"iteration":624,"passed_time":1.558117179,"remaining_time":0.9348703075},
{"learn":[0.7012105387],"iteration":625,"passed_time":1.560305248,"remaining_time":0.9321951481},
{"learn":[0.7010602034],"iteration":626,"passed_time":1.563196645,"remaining_time":0.9299399501},
{"learn":[0.7008538465],"iteration":627,"passed_time":1.565480255,"remaining_time":0.9273226989},
{"learn":[0.700763738],"iteration":628,"passed_time":1.567827656,"remaining_time":0.9247441342},
{"learn":[0.7006450092],"iteration":629,"passed_time":1.570223182,"remaining_time":0.9221945672},
{"learn":[0.7005269932],"iteration":630,"passed_time":1.572812665,"remaining_time":0.9197589117},
{"learn":[0.7001318589],"iteration":631,"passed_time":1.575229107,"remaining_time":0.9172220116},
{"learn":[0.699932577],"iteration":632,"passed_time":1.577690424,"remaining_time":0.9147115096},
{"learn":[0.6997651023],"iteration":633,"passed_time":1.580074283,"remaining_time":0.9121564473},
{"learn":[0.6995164843],"iteration":634,"passed_time":1.582996764,"remaining_time":0.9099115255},
{"learn":[0.6993357284],"iteration":635,"passed_time":1.585894911,"remaining_time":0.9076505466},
{"learn":[0.6992249873],"iteration":636,"passed_time":1.588242687,"remaining_time":0.9050739331},
{"learn":[0.6987900999],"iteration":637,"passed_time":1.590724587,"remaining_time":0.9025741388},
{"learn":[0.6986800773],"iteration":638,"passed_time":1.59304078,"remaining_time":0.899980785},
{"learn":[0.6984957412],"iteration":639,"passed_time":1.595610721,"remaining_time":0.8975310308},
{"learn":[0.6983823943],"iteration":640,"passed_time":1.598223704,"remaining_time":0.8951050074},
{"learn":[0.6981501742],"iteration":641,"passed_time":1.600563188,"remaining_time":0.8925258901},
{"learn":[0.6977020821],"iteration":642,"passed_time":1.603690418,"remaining_time":0.890384882},
{"learn":[0.6971848378],"iteration":643,"passed_time":1.606062527,"remaining_time":0.8878233844},
{"learn":[0.6968523137],"iteration":644,"passed_time":1.60836622,"remaining_time":0.8852248187},
{"learn":[0.6966851134],"iteration":645,"passed_time":1.610711204,"remaining_time":0.8826497931},
{"learn":[0.6961249283],"iteration":646,"passed_time":1.613220271,"remaining_time":0.880165001},
{"learn":[0.696010336],"iteration":647,"passed_time":1.616299125,"remaining_time":0.8779896484},
{"learn":[0.6957001034],"iteration":648,"passed_time":1.618735693,"remaining_time":0.8754641419},
{"learn":[0.6954893999],"iteration":649,"passed_time":1.621546674,"remaining_time":0.8731405167},
{"learn":[0.6952630428],"iteration":650,"passed_time":1.624014032,"remaining_time":0.8706311787},
{"learn":[0.6945432967],"iteration":651,"passed_time":1.62686218,"remaining_time":0.8683252128},
{"learn":[0.6943672745],"iteration":652,"passed_time":1.629738536,"remaining_time":0.8660325758},
{"learn":[0.6941523586],"iteration":653,"passed_time":1.632529643,"remaining_time":0.8636930525},
{"learn":[0.6938627683],"iteration":654,"passed_time":1.634898418,"remaining_time":0.8611297013},
{"learn":[0.69370856],"iteration":655,"passed_time":1.637575776,"remaining_time":0.8587287604},
{"learn":[0.6936012246],"iteration":656,"passed_time":1.640068551,"remaining_time":0.8562306132},
{"learn":[0.6932119079],"iteration":657,"passed_time":1.642549284,"remaining_time":0.8537262237},
{"learn":[0.6926213856],"iteration":658,"passed_time":1.644852686,"remaining_time":0.8511301453},
{"learn":[0.6925515948],"iteration":659,"passed_time":1.647198087,"remaining_time":0.8485565901},
{"learn":[0.6923888129],"iteration":660,"passed_time":1.649501655,"remaining_time":0.8459622707},
{"learn":[0.6921505326],"iteration":661,"passed_time":1.652058471,"remaining_time":0.8434981317},
{"learn":[0.6908667128],"iteration":662,"passed_time":1.654583413,"remaining_time":0.8410175113},
{"learn":[0.6905511552],"iteration":663,"passed_time":1.657082646,"remaining_time":0.8385237485},
{"learn":[0.6903752749],"iteration":664,"passed_time":1.659624546,"remaining_time":0.8360514629},
{"learn":[0.6903067085],"iteration":665,"passed_time":1.662182945,"remaining_time":0.8335872428},
{"learn":[0.6901180026],"iteration":666,"passed_time":1.664849844,"remaining_time":0.8311769087},
{"learn":[0.6892933969],"iteration":667,"passed_time":1.667294245,"remaining_time":0.8286552234},
{"learn":[0.6887090755],"iteration":668,"passed_time":1.669900936,"remaining_time":0.8262140653},
{"learn":[0.6885613413],"iteration":669,"passed_time":1.672770625,"remaining_time":0.8239019496},
{"learn":[0.6884718883],"iteration":670,"passed_time":1.675101693,"remaining_time":0.8213240788},
{"learn":[0.6880674812],"iteration":671,"passed_time":1.677699384,"remaining_time":0.8188770802},
{"learn":[0.6879200061],"iteration":672,"passed_time":1.680160409,"remaining_time":0.81636323},
{"learn":[0.6877039306],"iteration":673,"passed_time":1.682797183,"remaining_time":0.8139345426},
{"learn":[0.6872877641],"iteration":674,"passed_time":1.685075626,"remaining_time":0.811332709},
{"learn":[0.6871654251],"iteration":675,"passed_time":1.6877174,"remaining_time":0.808905973},
{"learn":[0.6869789753],"iteration":676,"passed_time":1.690075301,"remaining_time":0.8063431645},
{"learn":[0.6869053377],"iteration":677,"passed_time":1.692323328,"remaining_time":0.8037287783},
{"learn":[0.6867862294],"iteration":678,"passed_time":1.694811353,"remaining_time":0.8012289314},
{"learn":[0.6865126653],"iteration":679,"passed_time":1.697409461,"remaining_time":0.7987809228},
{"learn":[0.6864206392],"iteration":680,"passed_time":1.700135443,"remaining_time":0.7963923734},
{"learn":[0.6861974976],"iteration":681,"passed_time":1.702827967,"remaining_time":0.7939872337},
{"learn":[0.6860491218],"iteration":682,"passed_time":1.70527345,"remaining_time":0.7914665941},
{"learn":[0.6859462565],"iteration":683,"passed_time":1.707775309,"remaining_time":0.7889722187},
{"learn":[0.6858278689],"iteration":684,"passed_time":1.710844955,"remaining_time":0.7867389209},
{"learn":[0.6856418322],"iteration":685,"passed_time":1.713220898,"remaining_time":0.7841856586},
{"learn":[0.6853753696],"iteration":686,"passed_time":1.716284169,"remaining_time":0.7819460624},
{"learn":[0.6852755551],"iteration":687,"passed_time":1.718793944,"remaining_time":0.7794530675},
{"learn":[0.6851675146],"iteration":688,"passed_time":1.72129851,"remaining_time":0.7769576731},
{"learn":[0.6850102782],"iteration":689,"passed_time":1.724019201,"remaining_time":0.774559351},
{"learn":[0.6848334856],"iteration":690,"passed_time":1.726621475,"remaining_time":0.772107143},
{"learn":[0.6845765944],"iteration":691,"passed_time":1.728953168,"remaining_time":0.769534069},
{"learn":[0.6833700306],"iteration":692,"passed_time":1.731444401,"remaining_time":0.7670323683},
{"learn":[0.6826090262],"iteration":693,"passed_time":1.733696886,"remaining_time":0.7644254283},
{"learn":[0.6824422011],"iteration":694,"passed_time":1.736079121,"remaining_time":0.7618764486},
{"learn":[0.6823695956],"iteration":695,"passed_time":1.738461396,"remaining_time":0.7593279662},
{"learn":[0.6822462333],"iteration":696,"passed_time":1.740692673,"remaining_time":0.7567143185},
{"learn":[0.6818026752],"iteration":697,"passed_time":1.74316349,"remaining_time":0.7542054069},
{"learn":[0.6814021917],"iteration":698,"passed_time":1.745776723,"remaining_time":0.7517579307},
{"learn":[0.6812516278],"iteration":699,"passed_time":1.748312122,"remaining_time":0.7492766239},
{"learn":[0.6810959412],"iteration":700,"passed_time":1.751141437,"remaining_time":0.7469205273},
{"learn":[0.6809763023],"iteration":701,"passed_time":1.753595504,"remaining_time":0.7444037895},
{"learn":[0.680692248],"iteration":702,"passed_time":1.756030946,"remaining_time":0.7418793613},
{"learn":[0.6804812892],"iteration":703,"passed_time":1.758532555,"remaining_time":0.7393830059},
{"learn":[0.6802661852],"iteration":704,"passed_time":1.761334619,"remaining_time":0.7370123584},
{"learn":[0.6800229302],"iteration":705,"passed_time":1.763755978,"remaining_time":0.7344819512},
{"learn":[0.6798413031],"iteration":706,"passed_time":1.766418502,"remaining_time":0.7320517979},
{"learn":[0.678997748],"iteration":707,"passed_time":1.768955944,"remaining_time":0.7295694004},
{"learn":[0.6787365545],"iteration":708,"passed_time":1.771367677,"remaining_time":0.7270352527},
{"learn":[0.6784047504],"iteration":709,"passed_time":1.773732662,"remaining_time":0.7244823548},
{"learn":[0.6778038252],"iteration":710,"passed_time":1.776315395,"remaining_time":0.7220184937},
{"learn":[0.6775589482],"iteration":711,"passed_time":1.778683795,"remaining_time":0.7194676027},
{"learn":[0.6774678959],"iteration":712,"passed_time":1.781074113,"remaining_time":0.7169260455},
{"learn":[0.6767914572],"iteration":713,"passed_time":1.78345643,"remaining_time":0.7143817074},
{"learn":[0.675627735],"iteration":714,"passed_time":1.785960789,"remaining_time":0.7118864683},
{"learn":[0.6749688239],"iteration":715,"passed_time":1.788563355,"remaining_time":0.7094301575},
{"learn":[0.6747866713],"iteration":716,"passed_time":1.79085859,"remaining_time":0.7068521351},
{"learn":[0.6745766539],"iteration":717,"passed_time":1.793393531,"remaining_time":0.704369047},
{"learn":[0.6743572138],"iteration":718,"passed_time":1.796130929,"remaining_time":0.7019649391},
{"learn":[0.6741724617],"iteration":719,"passed_time":1.798648913,"remaining_time":0.6994745772},
{"learn":[0.6740639917],"iteration":720,"passed_time":1.80126752,"remaining_time":0.6970230765},
{"learn":[0.673945172],"iteration":721,"passed_time":1.803642463,"remaining_time":0.6944772918},
{"learn":[0.6738492732],"iteration":722,"passed_time":1.806412361,"remaining_time":0.6920832974},
{"learn":[0.6736970333],"iteration":723,"passed_time":1.80887347,"remaining_time":0.6895705492},
{"learn":[0.6735277976],"iteration":724,"passed_time":1.811196871,"remaining_time":0.6870057097},
{"learn":[0.6733253927],"iteration":725,"passed_time":1.813639105,"remaining_time":0.6844863839},
{"learn":[0.6731790242],"iteration":726,"passed_time":1.816480461,"remaining_time":0.6821171469},
{"learn":[0.6730206643],"iteration":727,"passed_time":1.819322734,"remaining_time":0.6797469554},
{"learn":[0.6729181789],"iteration":728,"passed_time":1.821574969,"remaining_time":0.6771561269},
{"learn":[0.6728124536],"iteration":729,"passed_time":1.824125618,"remaining_time":0.6746765985},
{"learn":[0.6725937091],"iteration":730,"passed_time":1.826958891,"remaining_time":0.6723008778},
{"learn":[0.6723744753],"iteration":731,"passed_time":1.829496541,"remaining_time":0.6698156734},
{"learn":[0.6721689589],"iteration":732,"passed_time":1.832019941,"remaining_time":0.6673251353},
{"learn":[0.6718951311],"iteration":733,"passed_time":1.834505008,"remaining_time":0.6648206158},
{"learn":[0.6715892197],"iteration":734,"passed_time":1.836783867,"remaining_time":0.6622418025},
{"learn":[0.6714456226],"iteration":735,"passed_time":1.839108935,"remaining_time":0.659680379},
{"learn":[0.6709053814],"iteration":736,"passed_time":1.841799209,"remaining_time":0.6572499213},
{"learn":[0.670768616],"iteration":737,"passed_time":1.844507483,"remaining_time":0.6548251497},
{"learn":[0.6706440011],"iteration":738,"passed_time":1.847043591,"remaining_time":0.6523388054},
{"learn":[0.6704942341],"iteration":739,"passed_time":1.849457658,"remaining_time":0.6498094475},
{"learn":[0.6701432401],"iteration":740,"passed_time":1.851843142,"remaining_time":0.6472704101},
{"learn":[0.6700329527],"iteration":741,"passed_time":1.854351667,"remaining_time":0.6447745689},
{"learn":[0.6699754682],"iteration":742,"passed_time":1.856775484,"remaining_time":0.6422493937},
{"learn":[0.6697998714],"iteration":743,"passed_time":1.859271385,"remaining_time":0.6397492936},
{"learn":[0.6695551868],"iteration":744,"passed_time":1.861840784,"remaining_time":0.6372743623},
{"learn":[0.6693512975],"iteration":745,"passed_time":1.86419156,"remaining_time":0.6347247403},
{"learn":[0.6686250226],"iteration":746,"passed_time":1.866664044,"remaining_time":0.6322168716},
{"learn":[0.6685204834],"iteration":747,"passed_time":1.869053528,"remaining_time":0.629681135},
{"learn":[0.6683861283],"iteration":748,"passed_time":1.871323846,"remaining_time":0.6271058549},
{"learn":[0.6680972975],"iteration":749,"passed_time":1.873694872,"remaining_time":0.6245649573},
{"learn":[0.6677107059],"iteration":750,"passed_time":1.876527561,"remaining_time":0.6221775803},
{"learn":[0.6675835573],"iteration":751,"passed_time":1.878924087,"remaining_time":0.6196451777},
{"learn":[0.667086486],"iteration":752,"passed_time":1.881555403,"remaining_time":0.6171901521},
{"learn":[0.6667963067],"iteration":753,"passed_time":1.883848346,"remaining_time":0.6146242615},
{"learn":[0.6666964663],"iteration":754,"passed_time":1.886157206,"remaining_time":0.6120642588},
{"learn":[0.6664974871],"iteration":755,"passed_time":1.888765647,"remaining_time":0.6096016108},
{"learn":[0.6663095546],"iteration":756,"passed_time":1.891509587,"remaining_time":0.6071820734},
{"learn":[0.6662390642],"iteration":757,"passed_time":1.894011403,"remaining_time":0.6046843795},
{"learn":[0.6657064101],"iteration":758,"passed_time":1.896410304,"remaining_time":0.6021539965},
{"learn":[0.6655429131],"iteration":759,"passed_time":1.898755914,"remaining_time":0.5996071306},
{"learn":[0.6654374976],"iteration":760,"passed_time":1.90104494,"remaining_time":0.5970430232},
{"learn":[0.665090791],"iteration":761,"passed_time":1.903591631,"remaining_time":0.5945601159},
{"learn":[0.6649105077],"iteration":762,"passed_time":1.906349571,"remaining_time":0.5921426585},
{"learn":[0.6648340123],"iteration":763,"passed_time":1.908580015,"remaining_time":0.5895613659},
{"learn":[0.6646727081],"iteration":764,"passed_time":1.911400746,"remaining_time":0.5871623207},
{"learn":[0.664550617],"iteration":765,"passed_time":1.91404627,"remaining_time":0.5847086517},
{"learn":[0.6637102489],"iteration":766,"passed_time":1.916408588,"remaining_time":0.5821684498},
{"learn":[0.663327249],"iteration":767,"passed_time":1.918844655,"remaining_time":0.5796509895},
{"learn":[0.6632128549],"iteration":768,"passed_time":1.921502929,"remaining_time":0.5772004897},
{"learn":[0.6630901769],"iteration":769,"passed_time":1.924215078,"remaining_time":0.5747655427},
{"learn":[0.6630177927],"iteration":770,"passed_time":1.926525896,"remaining_time":0.5722106746},
{"learn":[0.6628683426],"iteration":771,"passed_time":1.92908017,"remaining_time":0.5697283404},
{"learn":[0.6623554735],"iteration":772,"passed_time":1.931429696,"remaining_time":0.5671856935},
{"learn":[0.6622413866],"iteration":773,"passed_time":1.933957679,"remaining_time":0.5646956532},
{"learn":[0.6621181336],"iteration":774,"passed_time":1.936335164,"remaining_time":0.5621618217},
{"learn":[0.6614563785],"iteration":775,"passed_time":1.938984229,"remaining_time":0.5597067879},
{"learn":[0.6612953696],"iteration":776,"passed_time":1.941717003,"remaining_time":0.5572752788},
{"learn":[0.661224208],"iteration":777,"passed_time":1.944347694,"remaining_time":0.5548138663},
{"learn":[0.6610021647],"iteration":778,"passed_time":1.946583679,"remaining_time":0.5522400424},
{"learn":[0.6608886272],"iteration":779,"passed_time":1.948924413,"remaining_time":0.5496966294},
{"learn":[0.6603864762],"iteration":780,"passed_time":1.951655478,"remaining_time":0.5472631879},
{"learn":[0.6602612439],"iteration":781,"passed_time":1.954847124,"remaining_time":0.5449573824},
{"learn":[0.6601360988],"iteration":782,"passed_time":1.95739919,"remaining_time":0.5424720617},
{"learn":[0.6600354088],"iteration":783,"passed_time":1.959961382,"remaining_time":0.5399893602},
{"learn":[0.6594625804],"iteration":784,"passed_time":1.962306116,"remaining_time":0.537446898},
{"learn":[0.6593404047],"iteration":785,"passed_time":1.96466435,"remaining_time":0.5349086144},
{"learn":[0.658942101],"iteration":786,"passed_time":1.967104709,"remaining_time":0.5323930153},
{"learn":[0.6587962327],"iteration":787,"passed_time":1.96966615,"remaining_time":0.5299101826},
{"learn":[0.6586449462],"iteration":788,"passed_time":1.972206925,"remaining_time":0.5274216238},
{"learn":[0.6580620322],"iteration":789,"passed_time":1.9747197,"remaining_time":0.5249254899},
{"learn":[0.6579251437],"iteration":790,"passed_time":1.977159975,"remaining_time":0.5224101579},
{"learn":[0.6577728411],"iteration":791,"passed_time":1.979537043,"remaining_time":0.5198784153},
{"learn":[0.6576338696],"iteration":792,"passed_time":1.982231317,"remaining_time":0.5174298645},
{"learn":[0.657042556],"iteration":793,"passed_time":1.984703509,"remaining_time":0.5149230766},
{"learn":[0.6566628678],"iteration":794,"passed_time":1.987188242,"remaining_time":0.5124196096},
{"learn":[0.6565153775],"iteration":795,"passed_time":1.989776433,"remaining_time":0.509942704},
{"learn":[0.6564150451],"iteration":796,"passed_time":1.992162917,"remaining_time":0.5074141433},
{"learn":[0.6562854328],"iteration":797,"passed_time":1.994646818,"remaining_time":0.5049105979},
{"learn":[0.6561724975],"iteration":798,"passed_time":1.997306133,"remaining_time":0.50245123},
{"learn":[0.6560242868],"iteration":799,"passed_time":1.999844658,"remaining_time":0.4999611645},
{"learn":[0.6558923796],"iteration":800,"passed_time":2.001985477,"remaining_time":0.4973721722},
{"learn":[0.6557351401],"iteration":801,"passed_time":2.00451771,"remaining_time":0.4948809309},
{"learn":[0.6553606164],"iteration":802,"passed_time":2.006764779,"remaining_time":0.4923196281},
{"learn":[0.6552312265],"iteration":803,"passed_time":2.00956376,"remaining_time":0.4898936529},
{"learn":[0.6550901904],"iteration":804,"passed_time":2.011980036,"remaining_time":0.4873740459},
{"learn":[0.6548953018],"iteration":805,"passed_time":2.014458477,"remaining_time":0.4848696583},
{"learn":[0.6547293602],"iteration":806,"passed_time":2.01705771,"remaining_time":0.4823942231},
{"learn":[0.6546461798],"iteration":807,"passed_time":2.019416111,"remaining_time":0.4798612541},
{"learn":[0.6545933207],"iteration":808,"passed_time":2.02159618,"remaining_time":0.4772866136},
{"learn":[0.6544453112],"iteration":809,"passed_time":2.024453369,"remaining_time":0.474871778},
{"learn":[0.6543320549],"iteration":810,"passed_time":2.026896311,"remaining_time":0.472359313},
{"learn":[0.6538043386],"iteration":811,"passed_time":2.029763834,"remaining_time":0.4699453212},
{"learn":[0.6536904277],"iteration":812,"passed_time":2.032088527,"remaining_time":0.4674053561},
{"learn":[0.6535291341],"iteration":813,"passed_time":2.034666343,"remaining_time":0.464923759},
{"learn":[0.6533817426],"iteration":814,"passed_time":2.037024452,"remaining_time":0.4623920536},
{"learn":[0.652720195],"iteration":815,"passed_time":2.039841392,"remaining_time":0.4599642354},
{"learn":[0.6525607065],"iteration":816,"passed_time":2.042247876,"remaining_time":0.4574435267},
{"learn":[0.6524574379],"iteration":817,"passed_time":2.04460311,"remaining_time":0.4549116945},
{"learn":[0.6518234097],"iteration":818,"passed_time":2.047055136,"remaining_time":0.4524016844},
{"learn":[0.6517524792],"iteration":819,"passed_time":2.049670493,"remaining_time":0.4499276692},
{"learn":[0.6516749168],"iteration":820,"passed_time":2.051823271,"remaining_time":0.4473524549},
{"learn":[0.6515336605],"iteration":821,"passed_time":2.054486211,"remaining_time":0.4448887416},
{"learn":[0.651453763],"iteration":822,"passed_time":2.057142152,"remaining_time":0.4424230387},
{"learn":[0.6513975404],"iteration":823,"passed_time":2.059723426,"remaining_time":0.439940926},
{"learn":[0.6509464383],"iteration":824,"passed_time":2.062877655,"remaining_time":0.4375801087},
{"learn":[0.6507877465],"iteration":825,"passed_time":2.065402972,"remaining_time":0.4350848876},
{"learn":[0.6506508507],"iteration":826,"passed_time":2.067823664,"remaining_time":0.4325677073},
{"learn":[0.6505423486],"iteration":827,"passed_time":2.070041858,"remaining_time":0.4300086951},
{"learn":[0.6500048257],"iteration":828,"passed_time":2.072511508,"remaining_time":0.4275023738},
{"learn":[0.64989514],"iteration":829,"passed_time":2.075030366,"remaining_time":0.4250062196},
{"learn":[0.649538542],"iteration":830,"passed_time":2.077482725,"remaining_time":0.4224964868},
{"learn":[0.6494210511],"iteration":831,"passed_time":2.079810876,"remaining_time":0.4199618115},
{"learn":[0.6489483639],"iteration":832,"passed_time":2.082126944,"remaining_time":0.4174252097},
{"learn":[0.6482574539],"iteration":833,"passed_time":2.085008508,"remaining_time":0.4150016935},
{"learn":[0.6481885602],"iteration":834,"passed_time":2.087570158,"remaining_time":0.4125138635},
{"learn":[0.6478758813],"iteration":835,"passed_time":2.089871851,"remaining_time":0.4099748607},
{"learn":[0.6477641027],"iteration":836,"passed_time":2.092428334,"remaining_time":0.4074860435},
{"learn":[0.647647515],"iteration":837,"passed_time":2.095190024,"remaining_time":0.4050367349},
{"learn":[0.6475351238],"iteration":838,"passed_time":2.09796963,"remaining_time":0.4025901198},
{"learn":[0.6473622742],"iteration":839,"passed_time":2.100727154,"remaining_time":0.4001385055},
{"learn":[0.6469285245],"iteration":840,"passed_time":2.103254429,"remaining_time":0.3976426327},
{"learn":[0.6467335888],"iteration":841,"passed_time":2.105498955,"remaining_time":0.3950936282},
{"learn":[0.6465785845],"iteration":842,"passed_time":2.10822602,"remaining_time":0.3926352138},
{"learn":[0.6464359073],"iteration":843,"passed_time":2.110719504,"remaining_time":0.3901329889},
{"learn":[0.6462185116],"iteration":844,"passed_time":2.113995315,"remaining_time":0.3877742886},
{"learn":[0.6460704868],"iteration":845,"passed_time":2.117252252,"remaining_time":0.3854099844},
{"learn":[0.6459316342],"iteration":846,"passed_time":2.120186024,"remaining_time":0.3829851968},
{"learn":[0.6458265008],"iteration":847,"passed_time":2.122708966,"remaining_time":0.3804855693},
{"learn":[0.6457052364],"iteration":848,"passed_time":2.125740487,"remaining_time":0.3780763411},
{"learn":[0.645605001],"iteration":849,"passed_time":2.128522677,"remaining_time":0.3756216489},
{"learn":[0.6453981897],"iteration":850,"passed_time":2.130917828,"remaining_time":0.3730984211},
{"learn":[0.645260022],"iteration":851,"passed_time":2.133447728,"remaining_time":0.3705989011},
{"learn":[0.6451550805],"iteration":852,"passed_time":2.136248876,"remaining_time":0.3681460548},
{"learn":[0.6449876],"iteration":853,"passed_time":2.138607027,"remaining_time":0.365616658},
{"learn":[0.644518675],"iteration":854,"passed_time":2.141104052,"remaining_time":0.3631112135},
{"learn":[0.6442244828],"iteration":855,"passed_time":2.143456578,"remaining_time":0.3605814804},
{"learn":[0.6440916631],"iteration":856,"passed_time":2.14591727,"remaining_time":0.3580702095},
{"learn":[0.6439804818],"iteration":857,"passed_time":2.14842017,"remaining_time":0.3555660421},
{"learn":[0.6439019156],"iteration":858,"passed_time":2.150781279,"remaining_time":0.3530386034},
{"learn":[0.6437792021],"iteration":859,"passed_time":2.153079056,"remaining_time":0.3505012416},
{"learn":[0.6436707241],"iteration":860,"passed_time":2.155751079,"remaining_time":0.3480248549},
{"learn":[0.6434643309],"iteration":861,"passed_time":2.15847277,"remaining_time":0.3455559654},
{"learn":[0.6433765417],"iteration":862,"passed_time":2.161253043,"remaining_time":0.3430957901},
{"learn":[0.6433011674],"iteration":863,"passed_time":2.163976025,"remaining_time":0.3406258557},
{"learn":[0.6432166993],"iteration":864,"passed_time":2.166655382,"remaining_time":0.3381485278},
{"learn":[0.6431500905],"iteration":865,"passed_time":2.169154907,"remaining_time":0.3356429071},
{"learn":[0.6430615237],"iteration":866,"passed_time":2.171820389,"remaining_time":0.3331627587},
{"learn":[0.6428354461],"iteration":867,"passed_time":2.174328123,"remaining_time":0.3306581937},
{"learn":[0.6427260422],"iteration":868,"passed_time":2.176718815,"remaining_time":0.3281359779},
{"learn":[0.6426132418],"iteration":869,"passed_time":2.179053174,"remaining_time":0.3256056468},
{"learn":[0.6424809858],"iteration":870,"passed_time":2.1815352,"remaining_time":0.3230976358},
{"learn":[0.6422999848],"iteration":871,"passed_time":2.183926892,"remaining_time":0.3205764245},
{"learn":[0.6422174832],"iteration":872,"passed_time":2.186294085,"remaining_time":0.3180519459},
{"learn":[0.6419831438],"iteration":873,"passed_time":2.188651902,"remaining_time":0.3155264756},
{"learn":[0.6415593282],"iteration":874,"passed_time":2.191130427,"remaining_time":0.3130186325},
{"learn":[0.6413257737],"iteration":875,"passed_time":2.193545286,"remaining_time":0.3105018442},
{"learn":[0.641171005],"iteration":876,"passed_time":2.195898562,"remaining_time":0.3079766513},
{"learn":[0.6410795824],"iteration":877,"passed_time":2.198577211,"remaining_time":0.3054970612},
{"learn":[0.64096026],"iteration":878,"passed_time":2.201254443,"remaining_time":0.3030168233},
{"learn":[0.6408534585],"iteration":879,"passed_time":2.203791843,"remaining_time":0.3005170695},
{"learn":[0.6406863909],"iteration":880,"passed_time":2.206545242,"remaining_time":0.2980464061},
{"learn":[0.640409059],"iteration":881,"passed_time":2.208889018,"remaining_time":0.2955202994},
{"learn":[0.6398964699],"iteration":882,"passed_time":2.211172919,"remaining_time":0.2929866722},
{"learn":[0.6394371811],"iteration":883,"passed_time":2.213483987,"remaining_time":0.2904571748},
{"learn":[0.6393247265],"iteration":884,"passed_time":2.216118636,"remaining_time":0.2879702183},
{"learn":[0.6392692402],"iteration":885,"passed_time":2.218255872,"remaining_time":0.2854189271},
{"learn":[0.638885208],"iteration":886,"passed_time":2.220710647,"remaining_time":0.2829090227},
{"learn":[0.6387982179],"iteration":887,"passed_time":2.223309797,"remaining_time":0.2804174518},
{"learn":[0.6387136171],"iteration":888,"passed_time":2.225903446,"remaining_time":0.2779249522},
{"learn":[0.6385773634],"iteration":889,"passed_time":2.22906355,"remaining_time":0.2755022365},
{"learn":[0.6381297377],"iteration":890,"passed_time":2.231554784,"remaining_time":0.2729960397},
{"learn":[0.6380017772],"iteration":891,"passed_time":2.234225057,"remaining_time":0.270511554},
{"learn":[0.6379102422],"iteration":892,"passed_time":2.236660666,"remaining_time":0.2679985345},
{"learn":[0.6376225805],"iteration":893,"passed_time":2.239142025,"remaining_time":0.2654911126},
{"learn":[0.6375372579],"iteration":894,"passed_time":2.24155355,"remaining_time":0.2629755562},
{"learn":[0.6374687193],"iteration":895,"passed_time":2.243949284,"remaining_time":0.2604583991},
{"learn":[0.6371588818],"iteration":896,"passed_time":2.246522726,"remaining_time":0.2579619183},
{"learn":[0.6370510154],"iteration":897,"passed_time":2.24890021,"remaining_time":0.2554430083},
{"learn":[0.636922482],"iteration":898,"passed_time":2.251268152,"remaining_time":0.2529233408},
{"learn":[0.6368308905],"iteration":899,"passed_time":2.253747469,"remaining_time":0.2504163855},
{"learn":[0.6364620016],"iteration":900,"passed_time":2.256294202,"remaining_time":0.247916899},
{"learn":[0.6361106556],"iteration":901,"passed_time":2.25867927,"remaining_time":0.2453997433},
{"learn":[0.6359736536],"iteration":902,"passed_time":2.261340044,"remaining_time":0.2429124964},
{"learn":[0.6358418167],"iteration":903,"passed_time":2.263782778,"remaining_time":0.2404017109},
{"learn":[0.6357871609],"iteration":904,"passed_time":2.266113095,"remaining_time":0.2378792752},
{"learn":[0.6356830649],"iteration":905,"passed_time":2.268766536,"remaining_time":0.2353907885},
{"learn":[0.635583381],"iteration":906,"passed_time":2.271390394,"remaining_time":0.2328989048},
{"learn":[0.6354992987],"iteration":907,"passed_time":2.273894335,"remaining_time":0.2303945802},
{"learn":[0.6351472454],"iteration":908,"passed_time":2.276474818,"remaining_time":0.2278979191},
{"learn":[0.6349996167],"iteration":909,"passed_time":2.279139884,"remaining_time":0.2254094391},
{"learn":[0.6348907087],"iteration":910,"passed_time":2.281654075,"remaining_time":0.2229058317},
{"learn":[0.6347936304],"iteration":911,"passed_time":2.284296391,"remaining_time":0.2204145641},
{"learn":[0.634031692],"iteration":912,"passed_time":2.287045498,"remaining_time":0.2179331416},
{"learn":[0.6339024126],"iteration":913,"passed_time":2.289454982,"remaining_time":0.2154191777},
{"learn":[0.6337752108],"iteration":914,"passed_time":2.291856716,"remaining_time":0.2129047222},
{"learn":[0.6330696],"iteration":915,"passed_time":2.294601614,"remaining_time":0.2104219821},
{"learn":[0.6329776167],"iteration":916,"passed_time":2.297592886,"remaining_time":0.2079609701},
{"learn":[0.6328860098],"iteration":917,"passed_time":2.300018453,"remaining_time":0.2054482714},
{"learn":[0.6328060737],"iteration":918,"passed_time":2.302334605,"remaining_time":0.2029261186},
{"learn":[0.6324326583],"iteration":919,"passed_time":2.305388751,"remaining_time":0.200468587},
{"learn":[0.6323163955],"iteration":920,"passed_time":2.308260065,"remaining_time":0.1979940772},
{"learn":[0.6321803661],"iteration":921,"passed_time":2.310534508,"remaining_time":0.1954682122},
{"learn":[0.6320999347],"iteration":922,"passed_time":2.3130827,"remaining_time":0.192965729},
{"learn":[0.6316989573],"iteration":923,"passed_time":2.315504267,"remaining_time":0.1904527319},
{"learn":[0.6316111476],"iteration":924,"passed_time":2.318071375,"remaining_time":0.1879517331},
{"learn":[0.6314978538],"iteration":925,"passed_time":2.320658733,"remaining_time":0.1854522097},
{"learn":[0.631417555],"iteration":926,"passed_time":2.323145174,"remaining_time":0.1829445499},
{"learn":[0.6313221147],"iteration":927,"passed_time":2.325427201,"remaining_time":0.1804210759},
{"learn":[0.6311934682],"iteration":928,"passed_time":2.3280251,"remaining_time":0.1779222628},
{"learn":[0.6307744107],"iteration":929,"passed_time":2.330433334,"remaining_time":0.1754089606},
{"learn":[0.6306490317],"iteration":930,"passed_time":2.332880485,"remaining_time":0.1728987685},
{"learn":[0.6305085257],"iteration":931,"passed_time":2.335293469,"remaining_time":0.1703862187},
{"learn":[0.6304145754],"iteration":932,"passed_time":2.337616912,"remaining_time":0.1678674524},
{"learn":[0.630268702],"iteration":933,"passed_time":2.340279935,"remaining_time":0.1653731004},
{"learn":[0.63015628],"iteration":934,"passed_time":2.343074209,"remaining_time":0.1628875118},
{"learn":[0.6300534245],"iteration":935,"passed_time":2.345560567,"remaining_time":0.1603802097},
{"learn":[0.629968974],"iteration":936,"passed_time":2.348246799,"remaining_time":0.157886391},
{"learn":[0.6298824825],"iteration":937,"passed_time":2.350734324,"remaining_time":0.1553790278},
{"learn":[0.6297649998],"iteration":938,"passed_time":2.353512056,"remaining_time":0.1528905595},
{"learn":[0.629349106],"iteration":939,"passed_time":2.355807374,"remaining_time":0.1503706834},
{"learn":[0.6290870997],"iteration":940,"passed_time":2.358565981,"remaining_time":0.1478803325},
{"learn":[0.6290005188],"iteration":941,"passed_time":2.361369129,"remaining_time":0.1453921544},
{"learn":[0.6288844637],"iteration":942,"passed_time":2.363925987,"remaining_time":0.1428884212},
{"learn":[0.6285780436],"iteration":943,"passed_time":2.366111472,"remaining_time":0.140362545},
{"learn":[0.6284981686],"iteration":944,"passed_time":2.368628372,"remaining_time":0.1378566777},
{"learn":[0.6279177238],"iteration":945,"passed_time":2.37119823,"remaining_time":0.1353538102},
{"learn":[0.6273573405],"iteration":946,"passed_time":2.373851671,"remaining_time":0.1328554789},
{"learn":[0.6272097529],"iteration":947,"passed_time":2.376215571,"remaining_time":0.1303409385},
{"learn":[0.6270989512],"iteration":948,"passed_time":2.378950178,"remaining_time":0.1278466376},
{"learn":[0.6269928828],"iteration":949,"passed_time":2.381793368,"remaining_time":0.1253575457},
{"learn":[0.6267660587],"iteration":950,"passed_time":2.384236101,"remaining_time":0.1228470757},
{"learn":[0.6265586382],"iteration":951,"passed_time":2.386819959,"remaining_time":0.1203438635},
{"learn":[0.6264542049],"iteration":952,"passed_time":2.389721607,"remaining_time":0.1178561548},
{"learn":[0.6263989993],"iteration":953,"passed_time":2.392574921,"remaining_time":0.1153652478},
{"learn":[0.6259577397],"iteration":954,"passed_time":2.395109737,"remaining_time":0.112858574},
{"learn":[0.6258672699],"iteration":955,"passed_time":2.398006885,"remaining_time":0.1103685177},
{"learn":[0.6257715637],"iteration":956,"passed_time":2.400353953,"remaining_time":0.1078528944},
{"learn":[0.6256082782],"iteration":957,"passed_time":2.403015768,"remaining_time":0.105351422},
{"learn":[0.6255045923],"iteration":958,"passed_time":2.405419336,"remaining_time":0.1028385743},
{"learn":[0.625404518],"iteration":959,"passed_time":2.40779032,"remaining_time":0.1003245967},
{"learn":[0.6252864942],"iteration":960,"passed_time":2.410407302,"remaining_time":0.09782089989},
{"learn":[0.6247472528],"iteration":961,"passed_time":2.413197826,"remaining_time":0.09532382263},
{"learn":[0.6246785978],"iteration":962,"passed_time":2.415695309,"remaining_time":0.09281487687},
{"learn":[0.6246153259],"iteration":963,"passed_time":2.41806821,"remaining_time":0.09030130244},
{"learn":[0.6245214414],"iteration":964,"passed_time":2.420675734,"remaining_time":0.08779652922},
{"learn":[0.6244487475],"iteration":965,"passed_time":2.423213092,"remaining_time":0.08528907364},
{"learn":[0.6242636954],"iteration":966,"passed_time":2.425705742,"remaining_time":0.0827800305},
{"learn":[0.6241603569],"iteration":967,"passed_time":2.428122601,"remaining_time":0.08026851574},
{"learn":[0.6237635178],"iteration":968,"passed_time":2.430516419,"remaining_time":0.07775645921},
{"learn":[0.6236712191],"iteration":969,"passed_time":2.433236192,"remaining_time":0.0752547276},
{"learn":[0.6235745997],"iteration":970,"passed_time":2.436001382,"remaining_time":0.07275390328},
{"learn":[0.6234839537],"iteration":971,"passed_time":2.438233534,"remaining_time":0.07023717999},
{"learn":[0.6232607548],"iteration":972,"passed_time":2.441329763,"remaining_time":0.06774501913},
{"learn":[0.6231309964],"iteration":973,"passed_time":2.443995537,"remaining_time":0.06524012728},
{"learn":[0.6230482214],"iteration":974,"passed_time":2.446467104,"remaining_time":0.06272992575},
{"learn":[0.6225414789],"iteration":975,"passed_time":2.448922755,"remaining_time":0.060219412},
{"learn":[0.6215894221],"iteration":976,"passed_time":2.45130928,"remaining_time":0.05770738326},
{"learn":[0.6215237437],"iteration":977,"passed_time":2.453607432,"remaining_time":0.05519362321},
{"learn":[0.6212390008],"iteration":978,"passed_time":2.455994374,"remaining_time":0.05268220823},
{"learn":[0.6210963989],"iteration":979,"passed_time":2.45859394,"remaining_time":0.05017538654},
{"learn":[0.6208513362],"iteration":980,"passed_time":2.461071757,"remaining_time":0.04766601772},
{"learn":[0.6205474928],"iteration":981,"passed_time":2.463439241,"remaining_time":0.04515469078},
{"learn":[0.6200135163],"iteration":982,"passed_time":2.466045974,"remaining_time":0.04264779406},
{"learn":[0.619952243],"iteration":983,"passed_time":2.468371959,"remaining_time":0.04013612941},
{"learn":[0.6197316598],"iteration":984,"passed_time":2.47060086,"remaining_time":0.03762336336},
{"learn":[0.6196496077],"iteration":985,"passed_time":2.473295843,"remaining_time":0.03511779087},
{"learn":[0.6195862188],"iteration":986,"passed_time":2.476016324,"remaining_time":0.03261217043},
{"learn":[0.6192593009],"iteration":987,"passed_time":2.478410892,"remaining_time":0.03010215658},
{"learn":[0.6191158643],"iteration":988,"passed_time":2.481184832,"remaining_time":0.0275965957},
{"learn":[0.6185698808],"iteration":989,"passed_time":2.48369719,"remaining_time":0.0250878504},
{"learn":[0.6184736247],"iteration":990,"passed_time":2.48668592,"remaining_time":0.0225834241},
{"learn":[0.6183543138],"iteration":991,"passed_time":2.489069446,"remaining_time":0.02007314069},
{"learn":[0.6180465752],"iteration":992,"passed_time":2.491390764,"remaining_time":0.01756267407},
{"learn":[0.6179552684],"iteration":993,"passed_time":2.493737707,"remaining_time":0.0150527427},
{"learn":[0.6179077267],"iteration":994,"passed_time":2.496283648,"remaining_time":0.01254413893},
{"learn":[0.6173913604],"iteration":995,"passed_time":2.498860756,"remaining_time":0.01003558536},
{"learn":[0.6172577806],"iteration":996,"passed_time":2.501819028,"remaining_time":0.007528041207},
{"learn":[0.6171272773],"iteration":997,"passed_time":2.504697384,"remaining_time":0.005019433635},
{"learn":[0.6170386015],"iteration":998,"passed_time":2.507141784,"remaining_time":0.002509651436},
{"learn":[0.6168859241],"iteration":999,"passed_time":2.509400852,"remaining_time":0}
]}